[{"__type":"Werewolf.GameEngine.Creation.GameCreatedEvent, Werewolf.GameEngine","CreatedBy":"Rox","IsPrivate":false,"GameId":"rox-319","TimeStamp":"2021-07-21T21:18:32.1619834Z"},{"__type":"Werewolf.GameEngine.Creation.GameFormatSet, Werewolf.GameEngine","AnnounceOption":"speed-game","SetBy":"Rox","GameId":"rox-319","TimeStamp":"2021-07-21T21:18:33.0771767Z"},{"__type":"Werewolf.GameEngine.Creation.PlayerJoinedEvent, Werewolf.GameEngine","PlayerName":"ShaneMcC","GameId":"rox-319","TimeStamp":"2021-07-21T21:18:41.136411Z"},{"__type":"Werewolf.GameEngine.Creation.PlayerJoinedEvent, Werewolf.GameEngine","PlayerName":"NicolBolas","GameId":"rox-319","TimeStamp":"2021-07-21T21:18:41.6238987Z"},{"__type":"Werewolf.GameEngine.Creation.PlayerJoinedEvent, Werewolf.GameEngine","PlayerName":"SavvySteve","GameId":"rox-319","TimeStamp":"2021-07-21T21:18:53.0333575Z"},{"__type":"Werewolf.GameEngine.Creation.PlayerJoinedEvent, Werewolf.GameEngine","PlayerName":"Ellie","GameId":"rox-319","TimeStamp":"2021-07-21T21:19:07.8322301Z"},{"__type":"Werewolf.GameEngine.Creation.PlayerJoinedEvent, Werewolf.GameEngine","PlayerName":"ctsk","GameId":"rox-319","TimeStamp":"2021-07-21T21:19:11.3405762Z"},{"__type":"Werewolf.GameEngine.Creation.PlayerJoinedEvent, Werewolf.GameEngine","PlayerName":"laser","GameId":"rox-319","TimeStamp":"2021-07-21T21:20:28.4320459Z"},{"__type":"Werewolf.GameEngine.Creation.PlayerJoinedEvent, Werewolf.GameEngine","PlayerName":"ImTownSRSLY","GameId":"rox-319","TimeStamp":"2021-07-21T21:21:28.1894227Z"},{"__type":"Werewolf.GameEngine.Creation.PlayerJoinedEvent, Werewolf.GameEngine","PlayerName":"Ramen_Fluffy","GameId":"rox-319","TimeStamp":"2021-07-21T21:22:18.2179014Z"},{"__type":"Werewolf.GameEngine.Creation.PlayerJoinedEvent, Werewolf.GameEngine","PlayerName":"Phyton","GameId":"rox-319","TimeStamp":"2021-07-21T21:23:38.790571Z"},{"__type":"Werewolf.GameEngine.Creation.PlayerJoinedEvent, Werewolf.GameEngine","PlayerName":"Rox","GameId":"rox-319","TimeStamp":"2021-07-21T21:23:41.1122151Z"},{"__type":"Werewolf.GameEngine.Creation.PlayerJoinedEvent, Werewolf.GameEngine","PlayerName":"SnapDragon","GameId":"rox-319","TimeStamp":"2021-07-21T21:23:47.2891893Z"},{"__type":"Werewolf.GameEngine.Chatting.PendingGameMessage, Werewolf.GameEngine","PlayerName":"Phyton","Message":"Town are you hosting after this?","GameId":"rox-319","TimeStamp":"2021-07-21T21:24:09.615416Z"},{"__type":"Werewolf.GameEngine.Creation.GamePinged, Werewolf.GameEngine","PlayerName":"Rox","PlayerNames":["ShaneMcC","NicolBolas","SavvySteve","Ellie","ctsk","laser","ImTownSRSLY","Ramen_Fluffy","Phyton","Rox","SnapDragon"],"GameId":"rox-319","TimeStamp":"2021-07-21T21:28:16.1837733Z"},{"__type":"Werewolf.GameEngine.Chatting.PendingGameMessage, Werewolf.GameEngine","PlayerName":"ctsk","Message":"oi","GameId":"rox-319","TimeStamp":"2021-07-21T21:28:20.5319721Z"},{"__type":"Werewolf.GameEngine.Chatting.PendingGameMessage, Werewolf.GameEngine","PlayerName":"Ramen_Fluffy","Message":" ","GameId":"rox-319","TimeStamp":"2021-07-21T21:28:20.7536947Z"},{"__type":"Werewolf.GameEngine.Chatting.PendingGameMessage, Werewolf.GameEngine","PlayerName":"ShaneMcC","Message":".","GameId":"rox-319","TimeStamp":"2021-07-21T21:28:21.0869234Z"},{"__type":"Werewolf.GameEngine.Chatting.PendingGameMessage, Werewolf.GameEngine","PlayerName":"SavvySteve","Message":" something to make it clear you're here, please don't leave once saying you are ready","GameId":"rox-319","TimeStamp":"2021-07-21T21:28:28.5622527Z"},{"__type":"Werewolf.GameEngine.Chatting.PendingGameMessage, Werewolf.GameEngine","PlayerName":"NicolBolas","Message":" ","GameId":"rox-319","TimeStamp":"2021-07-21T21:28:29.5641446Z"},{"__type":"Werewolf.GameEngine.Chatting.PendingGameMessage, Werewolf.GameEngine","PlayerName":"laser","Message":"Shane","GameId":"rox-319","TimeStamp":"2021-07-21T21:28:31.485558Z"},{"__type":"Werewolf.GameEngine.Chatting.PendingGameMessage, Werewolf.GameEngine","PlayerName":"laser","Message":"I worry about his health","GameId":"rox-319","TimeStamp":"2021-07-21T21:28:38.6501861Z"},{"__type":"Werewolf.GameEngine.Creation.PlayerLeftEvent, Werewolf.GameEngine","PlayerName":"ShaneMcC","Reason":"Quit","GameId":"rox-319","TimeStamp":"2021-07-21T21:28:45.0132755Z"},{"__type":"Werewolf.GameEngine.Creation.PlayerJoinedEvent, Werewolf.GameEngine","PlayerName":"ShaneMcC","GameId":"rox-319","TimeStamp":"2021-07-21T21:28:45.4615949Z"},{"__type":"Werewolf.GameEngine.Chatting.PendingGameMessage, Werewolf.GameEngine","PlayerName":"ImTownSRSLY","Message":"l","GameId":"rox-319","TimeStamp":"2021-07-21T21:28:45.9042714Z"},{"__type":"Werewolf.GameEngine.Creation.PlayerLeftEvent, Werewolf.GameEngine","PlayerName":"SnapDragon","Reason":"Quit","GameId":"rox-319","TimeStamp":"2021-07-21T21:28:48.6873335Z"},{"__type":"Werewolf.GameEngine.Creation.PlayerJoinedEvent, Werewolf.GameEngine","PlayerName":"SnapDragon","GameId":"rox-319","TimeStamp":"2021-07-21T21:28:48.8510679Z"},{"__type":"Werewolf.GameEngine.Chatting.PendingGameMessage, Werewolf.GameEngine","PlayerName":"Rox","Message":"I will murder both of you","GameId":"rox-319","TimeStamp":"2021-07-21T21:28:56.4747863Z"},{"__type":"Werewolf.GameEngine.Chatting.PendingGameMessage, Werewolf.GameEngine","PlayerName":"ShaneMcC","Message":">:(","GameId":"rox-319","TimeStamp":"2021-07-21T21:29:09.5788532Z"},{"__type":"Werewolf.GameEngine.Chatting.PendingGameMessage, Werewolf.GameEngine","PlayerName":"ShaneMcC","Message":"No murdering :(","GameId":"rox-319","TimeStamp":"2021-07-21T21:29:12.0368725Z"},{"__type":"Werewolf.GameEngine.Chatting.PendingGameMessage, Werewolf.GameEngine","PlayerName":"Rox","Message":"Phy and ellie","GameId":"rox-319","TimeStamp":"2021-07-21T21:29:17.0690581Z"},{"__type":"Werewolf.GameEngine.Chatting.PendingGameMessage, Werewolf.GameEngine","PlayerName":"Rox","Message":"😔","GameId":"rox-319","TimeStamp":"2021-07-21T21:29:40.9966817Z"},{"__type":"Werewolf.GameEngine.Chatting.PendingGameMessage, Werewolf.GameEngine","PlayerName":"Rox","Message":"I dont have Shane seeking bow","GameId":"rox-319","TimeStamp":"2021-07-21T21:29:47.2502966Z"},{"__type":"Werewolf.GameEngine.Chatting.PendingGameMessage, Werewolf.GameEngine","PlayerName":"ShaneMcC","Message":"Good","GameId":"rox-319","TimeStamp":"2021-07-21T21:29:51.5715183Z"},{"__type":"Werewolf.GameEngine.Chatting.PendingGameMessage, Werewolf.GameEngine","PlayerName":"ShaneMcC","Message":"Too many other people do :(","GameId":"rox-319","TimeStamp":"2021-07-21T21:29:57.628238Z"},{"__type":"Werewolf.GameEngine.Chatting.PendingGameMessage, Werewolf.GameEngine","PlayerName":"Rox","Message":"Perish","GameId":"rox-319","TimeStamp":"2021-07-21T21:30:03.2250781Z"},{"__type":"Werewolf.GameEngine.Chatting.PendingGameMessage, Werewolf.GameEngine","PlayerName":"Ellie","Message":" ","GameId":"rox-319","TimeStamp":"2021-07-21T21:30:06.0952573Z"},{"__type":"Werewolf.GameEngine.Chatting.PendingGameMessage, Werewolf.GameEngine","PlayerName":"Rox","Message":"They killed me for the bow and I said I wouldnt kill the.","GameId":"rox-319","TimeStamp":"2021-07-21T21:30:32.599288Z"},{"__type":"Werewolf.GameEngine.Chatting.PendingGameMessage, Werewolf.GameEngine","PlayerName":"Rox","Message":"Them","GameId":"rox-319","TimeStamp":"2021-07-21T21:30:34.1532605Z"},{"__type":"Werewolf.GameEngine.Creation.GameStartedEvent, Werewolf.GameEngine","FirstDayLength":0,"NightLength":0,"DayLength":0,"DayDiscussionLength":0,"DefenceLength":0,"TrialLength":0,"LynchType":"MostVotes","PhaseTimeType":"VariableSpud","RoleAnnouncementMessageType":"Full","RoleList":["Alphawolf","Bloodletter","MasonLeader","Adjudicator","SpellWeaver","Protector","Villager","Villager","Villager","Villager","Villager"],"Host":"Rox","NumberOfMasonLeaders":0,"NumberOfDirewolves":0,"NumberOfWolves":0,"NumberOfShapeshifters":0,"NumberOfBloodhounds":0,"NumberOfLycans":0,"NumberOfSeers":0,"NumberOfProtectors":0,"NumberOfHuntsmen":0,"NumberOfGravediggers":0,"NumberOfGraverobbers":0,"NumberOfRevivers":0,"NumberOfHarlots":0,"NumberOfVampires":0,"NumberOfFamiliarStalkers":0,"NumberOfAlphaWolves":0,"NumberOfStalkers":0,"NumberOfMilitia":0,"NumberOfMessiahs":0,"NumberOfDjinn":0,"NumberOfSuccubi":0,"NumberOfWitches":0,"NumberOfShamans":0,"NumberOfPuppetmasters":0,"NumberOfTarotReaders":0,"NumberOfWitchHunters":0,"NumberOfBeholders":0,"NumberOfZealots":0,"NumberOfSleepWalkers":0,"NumberOfDemonlords":0,"NumberOfHellhounds":0,"GameId":"rox-319","TimeStamp":"2021-07-21T21:30:46.3346526Z"},{"__type":"Werewolf.GameEngine.Creation.NoLynchEnabled, Werewolf.GameEngine","GameId":"rox-319","TimeStamp":"2021-07-21T21:30:46.3346588Z"},{"__type":"Werewolf.GameEngine.Creation.GameSetToVariableLengthSpeedGameCycle, Werewolf.GameEngine","GameId":"rox-319","TimeStamp":"2021-07-21T21:30:46.3346605Z"},{"__type":"Werewolf.GameEngine.Creation.SkipDayEnabled, Werewolf.GameEngine","GameId":"rox-319","TimeStamp":"2021-07-21T21:30:46.3346613Z"},{"__type":"Werewolf.GameEngine.PlayerActivity.InactivitySmitingEnabled, Werewolf.GameEngine","GameId":"rox-319","TimeStamp":"2021-07-21T21:30:46.3346649Z"},{"__type":"Werewolf.GameEngine.Roles.SpellWeaverAssignedEvent, Werewolf.GameEngine","PlayerName":"SnapDragon","GameId":"rox-319","TimeStamp":"2021-07-21T21:30:46.336324Z"},{"__type":"Werewolf.GameEngine.Roles.MasonLeaderAssignedEvent, Werewolf.GameEngine","PlayerName":"Rox","GameId":"rox-319","TimeStamp":"2021-07-21T21:30:46.336746Z"},{"__type":"Werewolf.GameEngine.Roles.VillagerAssignedEvent, Werewolf.GameEngine","PlayerName":"ctsk","GameId":"rox-319","TimeStamp":"2021-07-21T21:30:46.3370341Z"},{"__type":"Werewolf.GameEngine.Roles.AlphawolfAssignedEvent, Werewolf.GameEngine","PlayerName":"ImTownSRSLY","GameId":"rox-319","TimeStamp":"2021-07-21T21:30:46.3372623Z"},{"__type":"Werewolf.GameEngine.Roles.VillagerAssignedEvent, Werewolf.GameEngine","PlayerName":"ShaneMcC","GameId":"rox-319","TimeStamp":"2021-07-21T21:30:46.339764Z"},{"__type":"Werewolf.GameEngine.Roles.VillagerAssignedEvent, Werewolf.GameEngine","PlayerName":"Phyton","GameId":"rox-319","TimeStamp":"2021-07-21T21:30:46.3399971Z"},{"__type":"Werewolf.GameEngine.Roles.AdjudicatorAssignedEvent, Werewolf.GameEngine","PlayerName":"SavvySteve","GameId":"rox-319","TimeStamp":"2021-07-21T21:30:46.3403651Z"},{"__type":"Werewolf.GameEngine.Roles.BloodletterAssignedEvent, Werewolf.GameEngine","PlayerName":"laser","GameId":"rox-319","TimeStamp":"2021-07-21T21:30:46.3409243Z"},{"__type":"Werewolf.GameEngine.Roles.VillagerAssignedEvent, Werewolf.GameEngine","PlayerName":"Ellie","GameId":"rox-319","TimeStamp":"2021-07-21T21:30:46.3412932Z"},{"__type":"Werewolf.GameEngine.Roles.ProtectorAssignedEvent, Werewolf.GameEngine","PlayerName":"Ramen_Fluffy","GameId":"rox-319","TimeStamp":"2021-07-21T21:30:46.3415169Z"},{"__type":"Werewolf.GameEngine.Roles.VillagerAssignedEvent, Werewolf.GameEngine","PlayerName":"NicolBolas","GameId":"rox-319","TimeStamp":"2021-07-21T21:30:46.3417337Z"},{"__type":"Werewolf.GameEngine.Core.ModeratorMessageEvent, Werewolf.GameEngine","Message":"There are: 1 SpellWeaver, 1 MasonLeader, 5 Villagers, 1 Alphawolf, 1 Adjudicator, 1 Bloodletter and 1 Protector.","GameId":"rox-319","TimeStamp":"2021-07-21T21:30:46.3418238Z"},{"__type":"Werewolf.GameEngine.Creation.GameSetupFinished, Werewolf.GameEngine","GameId":"rox-319","TimeStamp":"2021-07-21T21:30:46.3418285Z"},{"__type":"Werewolf.GameEngine.Roles.Village.Masons.MasonNightMessageEvent, Werewolf.GameEngine","PlayerName":"Rox","Message":"I am a Mason Leader","Recipients":["Rox"],"Eavesdroppers":["Default-Eavesdropper"],"GameId":"rox-319","TimeStamp":"2021-07-21T21:30:47.3105413Z"},{"__type":"Werewolf.GameEngine.Chatting.WerewolfNightMessageEvent, Werewolf.GameEngine","PlayerName":"ImTownSRSLY","Message":"I am an Alphawolf","Recipients":["ImTownSRSLY","laser"],"Eavesdroppers":["Default-Eavesdropper"],"GameId":"rox-319","TimeStamp":"2021-07-21T21:30:47.3107303Z"},{"__type":"Werewolf.GameEngine.Chatting.WerewolfNightMessageEvent, Werewolf.GameEngine","PlayerName":"laser","Message":"I am a Bloodletter","Recipients":["ImTownSRSLY","laser"],"Eavesdroppers":["Default-Eavesdropper"],"GameId":"rox-319","TimeStamp":"2021-07-21T21:30:47.3111122Z"},{"__type":"Werewolf.GameEngine.Chatting.VillageMessageEvent, Werewolf.GameEngine","PlayerName":"Ramen_Fluffy","Message":"What's a spell weaver?","GameId":"rox-319","TimeStamp":"2021-07-21T21:30:55.7633928Z"},{"__type":"Werewolf.GameEngine.Chatting.VillageMessageEvent, Werewolf.GameEngine","PlayerName":"Rox","Message":"They make shiny scrolls that do special things ","GameId":"rox-319","TimeStamp":"2021-07-21T21:31:05.8024345Z"},{"__type":"Werewolf.GameEngine.Chatting.VillageMessageEvent, Werewolf.GameEngine","PlayerName":"ShaneMcC","Message":"SpellYeeter.","GameId":"rox-319","TimeStamp":"2021-07-21T21:31:10.3855455Z"},{"__type":"Werewolf.GameEngine.Chatting.VillageMessageEvent, Werewolf.GameEngine","PlayerName":"Ramen_Fluffy","Message":"O.o","GameId":"rox-319","TimeStamp":"2021-07-21T21:31:10.8083729Z"},{"__type":"Werewolf.GameEngine.Chatting.VillageMessageEvent, Werewolf.GameEngine","PlayerName":"SavvySteve","Message":"https://unofficialhowtoplay.co.uk/index.php/Spell_Weaver","GameId":"rox-319","TimeStamp":"2021-07-21T21:31:16.3745247Z"},{"__type":"Werewolf.GameEngine.Chatting.VillageMessageEvent, Werewolf.GameEngine","PlayerName":"Ramen_Fluffy","Message":"thanks","GameId":"rox-319","TimeStamp":"2021-07-21T21:31:20.0915536Z"},{"__type":"Werewolf.GameEngine.Chatting.VillageMessageEvent, Werewolf.GameEngine","PlayerName":"laser","Message":"thank you","GameId":"rox-319","TimeStamp":"2021-07-21T21:31:20.913106Z"},{"__type":"Werewolf.GameEngine.Chatting.VillageMessageEvent, Werewolf.GameEngine","PlayerName":"Rox","Message":"Or agitate/reveal","GameId":"rox-319","TimeStamp":"2021-07-21T21:31:22.4662306Z"},{"__type":"Werewolf.GameEngine.Phases.Night.NightStartsSoonWarningGiven, Werewolf.GameEngine","FlavourText":"The shadows grow long...","GameId":"rox-319","TimeStamp":"2021-07-21T21:31:36.0928709Z"},{"__type":"Werewolf.GameEngine.Chatting.VillageMessageEvent, Werewolf.GameEngine","PlayerName":"Phyton","Message":"I am not evuls. Just putting my claim here. ","GameId":"rox-319","TimeStamp":"2021-07-21T21:31:42.6316248Z"},{"__type":"Werewolf.GameEngine.Phases.Night.NightStartedEvent, Werewolf.GameEngine","NightNumber":1,"PhaseLength":0,"GameId":"rox-319","TimeStamp":"2021-07-21T21:32:06.2121649Z"},{"__type":"Werewolf.GameEngine.Roles.ValidPrimaryNightTargetsShown, Werewolf.GameEngine","PlayerWithRole":"ImTownSRSLY","PlayerNames":["SnapDragon","Rox","ctsk","ShaneMcC","Phyton","SavvySteve","Ellie","Ramen_Fluffy","NicolBolas"],"ActionName":"Kill","Message":"The wolfpack have 1 kill tonight","DetailedDescription":null,"RoleOptions":null,"GameId":"rox-319","TimeStamp":"2021-07-21T21:32:06.2121962Z"},{"__type":"Werewolf.GameEngine.Roles.ValidPrimaryNightTargetsShown, Werewolf.GameEngine","PlayerWithRole":"Rox","PlayerNames":["SnapDragon","ctsk","ImTownSRSLY","ShaneMcC","Phyton","SavvySteve","laser","Ellie","Ramen_Fluffy","NicolBolas"],"ActionName":"Recruit","Message":null,"DetailedDescription":null,"RoleOptions":null,"GameId":"rox-319","TimeStamp":"2021-07-21T21:32:06.2125348Z"},{"__type":"Werewolf.GameEngine.Roles.ValidSecondaryNightTargetsShown, Werewolf.GameEngine","PlayerWithRole":"ImTownSRSLY","PlayerNames":["ImTownSRSLY"],"ActionName":"Enrage","Message":null,"GameId":"rox-319","TimeStamp":"2021-07-21T21:32:06.2128886Z"},{"__type":"Werewolf.GameEngine.Roles.ValidPrimaryNightTargetsShown, Werewolf.GameEngine","PlayerWithRole":"SavvySteve","PlayerNames":["SnapDragon","Rox","ctsk","ImTownSRSLY","ShaneMcC","Phyton","laser","Ellie","Ramen_Fluffy","NicolBolas"],"ActionName":"Check","Message":null,"DetailedDescription":null,"RoleOptions":null,"GameId":"rox-319","TimeStamp":"2021-07-21T21:32:06.2131898Z"},{"__type":"Werewolf.GameEngine.Roles.ValidPrimaryNightTargetsShown, Werewolf.GameEngine","PlayerWithRole":"laser","PlayerNames":["SnapDragon","Rox","ctsk","ImTownSRSLY","ShaneMcC","Phyton","SavvySteve","Ellie","Ramen_Fluffy","NicolBolas"],"ActionName":"Mark","Message":null,"DetailedDescription":null,"RoleOptions":null,"GameId":"rox-319","TimeStamp":"2021-07-21T21:32:06.2133655Z"},{"__type":"Werewolf.GameEngine.Roles.ValidPrimaryNightTargetsShown, Werewolf.GameEngine","PlayerWithRole":"Ramen_Fluffy","PlayerNames":["SnapDragon","Rox","ctsk","ImTownSRSLY","ShaneMcC","Phyton","SavvySteve","laser","Ellie","Ramen_Fluffy","NicolBolas"],"ActionName":"Protect","Message":null,"DetailedDescription":null,"RoleOptions":null,"GameId":"rox-319","TimeStamp":"2021-07-21T21:32:06.2133729Z"},{"__type":"Werewolf.GameEngine.Roles.NightTargetChosenEvent, Werewolf.GameEngine","Confirmation":"Tonight you will try to recruit $laser","AlliesConfirmation":null,"Allies":null,"PlayerWithRole":"Rox","Role":"MasonLeader","Target":"laser","GameId":"rox-319","TimeStamp":"2021-07-21T21:32:18.4009415Z"},{"__type":"Werewolf.GameEngine.Roles.NightTargetChosenEvent, Werewolf.GameEngine","Confirmation":"Tonight you will ascertain whether or not $Rox is capable of murder","AlliesConfirmation":null,"Allies":null,"PlayerWithRole":"SavvySteve","Role":"Adjudicator","Target":"Rox","GameId":"rox-319","TimeStamp":"2021-07-21T21:32:21.2576735Z"},{"__type":"Werewolf.GameEngine.Chatting.WerewolfNightMessageEvent, Werewolf.GameEngine","PlayerName":"laser","Message":"right I should also look up what the Bloodletter does","Recipients":["ImTownSRSLY","laser"],"Eavesdroppers":[],"GameId":"rox-319","TimeStamp":"2021-07-21T21:32:21.5407467Z"},{"__type":"Werewolf.GameEngine.Roles.NightTargetChosenEvent, Werewolf.GameEngine","Confirmation":"Tonight you will weave a spell for $Rox","AlliesConfirmation":null,"Allies":null,"PlayerWithRole":"SnapDragon","Role":"Spell Weaver","Target":"Rox","GameId":"rox-319","TimeStamp":"2021-07-21T21:32:22.9898709Z"},{"__type":"Werewolf.GameEngine.Chatting.WerewolfNightMessageEvent, Werewolf.GameEngine","PlayerName":"ImTownSRSLY","Message":"mark one as wolf","Recipients":["ImTownSRSLY","laser"],"Eavesdroppers":[],"GameId":"rox-319","TimeStamp":"2021-07-21T21:32:26.8317662Z"},{"__type":"Werewolf.GameEngine.Roles.NightTargetChosenEvent, Werewolf.GameEngine","Confirmation":"Tonight you will protect $Ramen_Fluffy from harm","AlliesConfirmation":null,"Allies":null,"PlayerWithRole":"Ramen_Fluffy","Role":"Protector","Target":"Ramen_Fluffy","GameId":"rox-319","TimeStamp":"2021-07-21T21:32:26.9123187Z"},{"__type":"Werewolf.GameEngine.Roles.NightTargetChosenEvent, Werewolf.GameEngine","Confirmation":"Tonight you will mark $ShaneMcC with wolf blood","AlliesConfirmation":"Tonight $laser will mark $ShaneMcC with wolf blood","Allies":["ImTownSRSLY"],"PlayerWithRole":"laser","Role":"Bloodletter","Target":"ShaneMcC","GameId":"rox-319","TimeStamp":"2021-07-21T21:32:33.4590101Z"},{"__type":"Werewolf.GameEngine.Chatting.WerewolfNightMessageEvent, Werewolf.GameEngine","PlayerName":"ImTownSRSLY","Message":"who do I need to kill for rox tobe wolf","Recipients":["ImTownSRSLY","laser"],"Eavesdroppers":[],"GameId":"rox-319","TimeStamp":"2021-07-21T21:32:33.9221159Z"},{"__type":"Werewolf.GameEngine.Chatting.WerewolfNightMessageEvent, Werewolf.GameEngine","PlayerName":"ImTownSRSLY","Message":"shane and snap?","Recipients":["ImTownSRSLY","laser"],"Eavesdroppers":[],"GameId":"rox-319","TimeStamp":"2021-07-21T21:32:37.9750181Z"},{"__type":"Werewolf.GameEngine.Chatting.WerewolfNightMessageEvent, Werewolf.GameEngine","PlayerName":"laser","Message":"bit obvious?","Recipients":["ImTownSRSLY","laser"],"Eavesdroppers":[],"GameId":"rox-319","TimeStamp":"2021-07-21T21:32:43.0687616Z"},{"__type":"Werewolf.GameEngine.Chatting.WerewolfNightMessageEvent, Werewolf.GameEngine","PlayerName":"laser","Message":"your free choice I guess :)","Recipients":["ImTownSRSLY","laser"],"Eavesdroppers":[],"GameId":"rox-319","TimeStamp":"2021-07-21T21:33:02.4137963Z"},{"__type":"Werewolf.GameEngine.Chatting.WerewolfNightMessageEvent, Werewolf.GameEngine","PlayerName":"ImTownSRSLY","Message":"who to kill thwn?","Recipients":["ImTownSRSLY","laser"],"Eavesdroppers":[],"GameId":"rox-319","TimeStamp":"2021-07-21T21:33:02.4257232Z"},{"__type":"Werewolf.GameEngine.Phases.Night.WerewolfVoteEvent, Werewolf.GameEngine","Werewolf":"ImTownSRSLY","Target":"Phyton","Recipients":["ImTownSRSLY","laser"],"MaxKillCount":1,"ThisKill":1,"GameId":"rox-319","TimeStamp":"2021-07-21T21:33:20.2663862Z"},{"__type":"Werewolf.GameEngine.Roles.NightTargetChosenEvent, Werewolf.GameEngine","Confirmation":"Tonight you will protect $Phyton from harm","AlliesConfirmation":null,"Allies":null,"PlayerWithRole":"Ramen_Fluffy","Role":"Protector","Target":"Phyton","GameId":"rox-319","TimeStamp":"2021-07-21T21:33:20.7245609Z"},{"__type":"Werewolf.GameEngine.Roles.Werewolves.Alphawolf.AlphawolfEnraged, Werewolf.GameEngine","PlayerName":"ImTownSRSLY","Recipients":["ImTownSRSLY","laser"],"Allies":["laser"],"GameId":"rox-319","TimeStamp":"2021-07-21T21:33:22.3567932Z"},{"__type":"Werewolf.GameEngine.Roles.ValidPrimaryNightTargetsShown, Werewolf.GameEngine","PlayerWithRole":"ImTownSRSLY","PlayerNames":["SnapDragon","Rox","ctsk","ShaneMcC","Phyton","SavvySteve","Ellie","Ramen_Fluffy","NicolBolas"],"ActionName":"Slaughter","Message":null,"DetailedDescription":null,"RoleOptions":null,"GameId":"rox-319","TimeStamp":"2021-07-21T21:33:22.3568198Z"},{"__type":"Werewolf.GameEngine.Roles.Werewolves.Alphawolf.AlphawolfTargetChosen, Werewolf.GameEngine","PlayerName":"ImTownSRSLY","Target":"Ramen_Fluffy","Recipients":["ImTownSRSLY","laser"],"Allies":["laser"],"GameId":"rox-319","TimeStamp":"2021-07-21T21:33:23.3609254Z"},{"__type":"Werewolf.GameEngine.Roles.ValidPrimaryNightTargetsShown, Werewolf.GameEngine","PlayerWithRole":"ImTownSRSLY","PlayerNames":["SnapDragon","Rox","ctsk","ShaneMcC","Phyton","SavvySteve","Ellie","Ramen_Fluffy","NicolBolas"],"ActionName":"Kill","Message":null,"DetailedDescription":null,"RoleOptions":null,"GameId":"rox-319","TimeStamp":"2021-07-21T21:33:23.3609466Z"},{"__type":"Werewolf.GameEngine.Phases.Day.DayStartsSoonWarningGiven, Werewolf.GameEngine","FlavourText":"It will soon be day...","GameId":"rox-319","TimeStamp":"2021-07-21T21:33:36.4778836Z"},{"__type":"Werewolf.GameEngine.Chatting.WerewolfNightMessageEvent, Werewolf.GameEngine","PlayerName":"ImTownSRSLY","Message":"I got friggin seer checked the last 2","Recipients":["ImTownSRSLY","laser"],"Eavesdroppers":[],"GameId":"rox-319","TimeStamp":"2021-07-21T21:33:39.4347846Z"},{"__type":"Werewolf.GameEngine.Chatting.WerewolfNightMessageEvent, Werewolf.GameEngine","PlayerName":"laser","Message":"u/l","Recipients":["ImTownSRSLY","laser"],"Eavesdroppers":[],"GameId":"rox-319","TimeStamp":"2021-07-21T21:33:51.0790373Z"},{"__type":"Werewolf.GameEngine.Roles.Werewolves.Bloodletter.PlayerMarkedByBloodletter, Werewolf.GameEngine","PlayerWithRole":"laser","Target":"ShaneMcC","NightNumber":1,"GameId":"rox-319","TimeStamp":"2021-07-21T21:34:06.0078524Z"},{"__type":"Werewolf.GameEngine.Roles.MorningReportShown, Werewolf.GameEngine","Message":"$Rox is not a killer","PlayerWithRole":"SavvySteve","Role":"Adjudicator","GameId":"rox-319","TimeStamp":"2021-07-21T21:34:06.0089873Z"},{"__type":"Werewolf.GameEngine.Items.EnchantedScrollAllocated, Werewolf.GameEngine","PlayerName":"Rox","ItemId":"b6322bb8-95cf-4277-a7e5-0cbcfe70fda7","ItemOptions":["amplify-self-silence-neighbours","silence-self-amplify-neighbours"],"GameId":"rox-319","TimeStamp":"2021-07-21T21:34:06.0091976Z"},{"__type":"Werewolf.GameEngine.Roles.Village.Protector.ProtectorProtected, Werewolf.GameEngine","ProtectorName":"Ramen_Fluffy","Target":"Phyton","GameId":"rox-319","TimeStamp":"2021-07-21T21:34:06.010052Z"},{"__type":"Werewolf.GameEngine.Roles.Werewolves.Alphawolf.AlphawolfUsedEnrage, Werewolf.GameEngine","PlayerName":"ImTownSRSLY","Recipients":["ImTownSRSLY"],"GameId":"rox-319","TimeStamp":"2021-07-21T21:34:06.0100659Z"},{"__type":"Werewolf.GameEngine.Phases.Night.PlayerKilledEvent, Werewolf.GameEngine","PlayerName":"Ramen_Fluffy","CauseOfDeath":"Werewolf","GameId":"rox-319","TimeStamp":"2021-07-21T21:34:06.0100958Z"},{"__type":"Werewolf.GameEngine.Phases.Night.PlayerKilledEvent, Werewolf.GameEngine","PlayerName":"Rox","CauseOfDeath":"FailedRecruit","GameId":"rox-319","TimeStamp":"2021-07-21T21:34:06.010097Z"},{"__type":"Werewolf.GameEngine.Phases.Day.DayStartedEvent, Werewolf.GameEngine","DayNumber":2,"PhaseLength":0,"DiscussionLength":0,"GameId":"rox-319","TimeStamp":"2021-07-21T21:34:06.0101041Z"},{"__type":"Werewolf.GameEngine.Chatting.GhostMessageEvent, Werewolf.GameEngine","PlayerName":"Rox","Message":"Welp laser is a wolf","Recipients":["Ramen_Fluffy","Rox"],"GameId":"rox-319","TimeStamp":"2021-07-21T21:34:11.8554947Z"},{"__type":"Werewolf.GameEngine.Chatting.GhostMessageEvent, Werewolf.GameEngine","PlayerName":"Ramen_Fluffy","Message":"oof","Recipients":["Ramen_Fluffy","Rox"],"GameId":"rox-319","TimeStamp":"2021-07-21T21:34:14.8715883Z"},{"__type":"Werewolf.GameEngine.Chatting.GhostMessageEvent, Werewolf.GameEngine","PlayerName":"Ramen_Fluffy","Message":"prot here","Recipients":["Ramen_Fluffy","Rox"],"GameId":"rox-319","TimeStamp":"2021-07-21T21:34:16.5230603Z"},{"__type":"Werewolf.GameEngine.Chatting.GhostMessageEvent, Werewolf.GameEngine","PlayerName":"Rox","Message":"Mason leader","Recipients":["Ramen_Fluffy","Rox"],"GameId":"rox-319","TimeStamp":"2021-07-21T21:34:23.2246812Z"},{"__type":"Werewolf.GameEngine.Phases.Day.VillageNominationsOpenedEvent, Werewolf.GameEngine","TimeLeft":0,"GameId":"rox-319","TimeStamp":"2021-07-21T21:34:36.3026968Z"},{"__type":"Werewolf.GameEngine.Phases.Day.NoLynchOptionAvailable, Werewolf.GameEngine","GameId":"rox-319","TimeStamp":"2021-07-21T21:34:36.3026989Z"},{"__type":"Werewolf.GameEngine.Phases.Day.SkipDayOptionAvailable, Werewolf.GameEngine","GameId":"rox-319","TimeStamp":"2021-07-21T21:34:36.3026996Z"},{"__type":"Werewolf.GameEngine.Chatting.GhostMessageEvent, Werewolf.GameEngine","PlayerName":"Ramen_Fluffy","Message":"I was going to prot myself but usually dont die n1","Recipients":["Ramen_Fluffy","Rox"],"GameId":"rox-319","TimeStamp":"2021-07-21T21:34:37.9460281Z"},{"__type":"Werewolf.GameEngine.Chatting.GhostMessageEvent, Werewolf.GameEngine","PlayerName":"Rox","Message":":(","Recipients":["Ramen_Fluffy","Rox"],"GameId":"rox-319","TimeStamp":"2021-07-21T21:34:42.7359635Z"},{"__type":"Werewolf.GameEngine.Chatting.GhostMessageEvent, Werewolf.GameEngine","PlayerName":"Rox","Message":"I would kill myself naturally","Recipients":["Ramen_Fluffy","Rox"],"GameId":"rox-319","TimeStamp":"2021-07-21T21:34:49.6803099Z"},{"__type":"Werewolf.GameEngine.Chatting.GhostMessageEvent, Werewolf.GameEngine","PlayerName":"Ramen_Fluffy","Message":"so I prot phy for not being evul","Recipients":["Ramen_Fluffy","Rox"],"GameId":"rox-319","TimeStamp":"2021-07-21T21:34:51.9199974Z"},{"__type":"Werewolf.GameEngine.Chatting.VillageMessageEvent, Werewolf.GameEngine","PlayerName":"ShaneMcC","Message":"Killing the host.","GameId":"rox-319","TimeStamp":"2021-07-21T21:34:53.4299248Z"},{"__type":"Werewolf.GameEngine.Chatting.VillageMessageEvent, Werewolf.GameEngine","PlayerName":"ShaneMcC","Message":"smh.","GameId":"rox-319","TimeStamp":"2021-07-21T21:34:54.8354013Z"},{"__type":"Werewolf.GameEngine.Chatting.VillageMessageEvent, Werewolf.GameEngine","PlayerName":"ShaneMcC","Message":"wow.","GameId":"rox-319","TimeStamp":"2021-07-21T21:34:55.6876293Z"},{"__type":"Werewolf.GameEngine.Chatting.VillageMessageEvent, Werewolf.GameEngine","PlayerName":"Phyton","Message":"I think ML des","GameId":"rox-319","TimeStamp":"2021-07-21T21:34:56.637637Z"},{"__type":"Werewolf.GameEngine.Chatting.VillageMessageEvent, Werewolf.GameEngine","PlayerName":"ShaneMcC","Message":"just... wow.","GameId":"rox-319","TimeStamp":"2021-07-21T21:34:57.3504047Z"},{"__type":"Werewolf.GameEngine.Chatting.VillageMessageEvent, Werewolf.GameEngine","PlayerName":"Phyton","Message":"*ded","GameId":"rox-319","TimeStamp":"2021-07-21T21:34:59.4311108Z"},{"__type":"Werewolf.GameEngine.Chatting.GhostMessageEvent, Werewolf.GameEngine","PlayerName":"Ramen_Fluffy","Message":"Wed 21:34I would kill myself naturally --> D:","Recipients":["Ramen_Fluffy","Rox"],"GameId":"rox-319","TimeStamp":"2021-07-21T21:35:11.6070597Z"},{"__type":"Werewolf.GameEngine.Chatting.GhostMessageEvent, Werewolf.GameEngine","PlayerName":"Rox","Message":"😩","Recipients":["Ramen_Fluffy","Rox"],"GameId":"rox-319","TimeStamp":"2021-07-21T21:35:23.9413438Z"},{"__type":"Werewolf.GameEngine.Chatting.VillageMessageEvent, Werewolf.GameEngine","PlayerName":"ShaneMcC","Message":"I never kill Rox when evil. I let her kill herself trying to visit me.","GameId":"rox-319","TimeStamp":"2021-07-21T21:35:33.4776247Z"},{"__type":"Werewolf.GameEngine.Phases.Day.VillageNominationEvent, Werewolf.GameEngine","PlayerName":"ShaneMcC","Target":"SnapDragon","GameId":"rox-319","TimeStamp":"2021-07-21T21:36:01.0627056Z"},{"__type":"Werewolf.GameEngine.Phases.Day.VillageNominationEvent, Werewolf.GameEngine","PlayerName":"SnapDragon","Target":"ImTownSRSLY","GameId":"rox-319","TimeStamp":"2021-07-21T21:36:15.559443Z"},{"__type":"Werewolf.GameEngine.Phases.VoteForNoLynchCast, Werewolf.GameEngine","PlayerName":"SavvySteve","GameId":"rox-319","TimeStamp":"2021-07-21T21:36:20.3602865Z"},{"__type":"Werewolf.GameEngine.Phases.VoteForNoLynchCast, Werewolf.GameEngine","PlayerName":"NicolBolas","GameId":"rox-319","TimeStamp":"2021-07-21T21:36:26.5168341Z"},{"__type":"Werewolf.GameEngine.Phases.VoteForNoLynchCast, Werewolf.GameEngine","PlayerName":"laser","GameId":"rox-319","TimeStamp":"2021-07-21T21:36:39.1062236Z"},{"__type":"Werewolf.GameEngine.Chatting.VillageMessageEvent, Werewolf.GameEngine","PlayerName":"Phyton","Message":"Savvy look innocent","GameId":"rox-319","TimeStamp":"2021-07-21T21:36:39.3001974Z"},{"__type":"Werewolf.GameEngine.Phases.Day.VillageNominationEvent, Werewolf.GameEngine","PlayerName":"ctsk","Target":"ShaneMcC","GameId":"rox-319","TimeStamp":"2021-07-21T21:37:16.2445264Z"},{"__type":"Werewolf.GameEngine.Chatting.VillageMessageEvent, Werewolf.GameEngine","PlayerName":"ctsk","Message":"If ti was ML who would they recruit?","GameId":"rox-319","TimeStamp":"2021-07-21T21:37:25.5887601Z"},{"__type":"Werewolf.GameEngine.Phases.Day.VillageNominationEvent, Werewolf.GameEngine","PlayerName":"ImTownSRSLY","Target":"ShaneMcC","GameId":"rox-319","TimeStamp":"2021-07-21T21:37:27.7436693Z"},{"__type":"Werewolf.GameEngine.Phases.Day.VillageNominationEvent, Werewolf.GameEngine","PlayerName":"Ellie","Target":"ShaneMcC","GameId":"rox-319","TimeStamp":"2021-07-21T21:37:51.0246587Z"},{"__type":"Werewolf.GameEngine.Phases.Day.VillageNominationRetractedEvent, Werewolf.GameEngine","Target":"ShaneMcC","PlayerName":"ctsk","GameId":"rox-319","TimeStamp":"2021-07-21T21:37:55.6190475Z"},{"__type":"Werewolf.GameEngine.Phases.VoteForNoLynchCast, Werewolf.GameEngine","PlayerName":"ctsk","GameId":"rox-319","TimeStamp":"2021-07-21T21:37:55.6190496Z"},{"__type":"Werewolf.GameEngine.Phases.Day.VillageNominationRetractedEvent, Werewolf.GameEngine","Target":"ShaneMcC","PlayerName":"ImTownSRSLY","GameId":"rox-319","TimeStamp":"2021-07-21T21:37:59.3071774Z"},{"__type":"Werewolf.GameEngine.Phases.VoteForNoLynchCast, Werewolf.GameEngine","PlayerName":"ImTownSRSLY","GameId":"rox-319","TimeStamp":"2021-07-21T21:37:59.3071791Z"},{"__type":"Werewolf.GameEngine.Chatting.GhostMessageEvent, Werewolf.GameEngine","PlayerName":"Rox","Message":"Yeah nah they'd never guess who I tried recruiting","Recipients":["Ramen_Fluffy","Rox"],"GameId":"rox-319","TimeStamp":"2021-07-21T21:38:04.317435Z"},{"__type":"Werewolf.GameEngine.Phases.Day.VillageNominationRetractedEvent, Werewolf.GameEngine","Target":"ImTownSRSLY","PlayerName":"SnapDragon","GameId":"rox-319","TimeStamp":"2021-07-21T21:38:04.5507207Z"},{"__type":"Werewolf.GameEngine.Phases.VoteForNoLynchCast, Werewolf.GameEngine","PlayerName":"SnapDragon","GameId":"rox-319","TimeStamp":"2021-07-21T21:38:04.5507226Z"},{"__type":"Werewolf.GameEngine.Phases.Day.VillageNominationEvent, Werewolf.GameEngine","PlayerName":"Phyton","Target":"ImTownSRSLY","GameId":"rox-319","TimeStamp":"2021-07-21T21:38:05.5326593Z"},{"__type":"Werewolf.GameEngine.Chatting.GhostMessageEvent, Werewolf.GameEngine","PlayerName":"Ramen_Fluffy","Message":"snap went very hight pitch","Recipients":["Ramen_Fluffy","Rox"],"GameId":"rox-319","TimeStamp":"2021-07-21T21:38:18.1342037Z"},{"__type":"Werewolf.GameEngine.Chatting.GhostMessageEvent, Werewolf.GameEngine","PlayerName":"Rox","Message":"Yes","Recipients":["Ramen_Fluffy","Rox"],"GameId":"rox-319","TimeStamp":"2021-07-21T21:38:26.3456086Z"},{"__type":"Werewolf.GameEngine.Phases.Night.NightStartsSoonWarningGiven, Werewolf.GameEngine","FlavourText":"The day draws to a close...","GameId":"rox-319","TimeStamp":"2021-07-21T21:38:36.3502788Z"},{"__type":"Werewolf.GameEngine.Phases.VoteForSkipDayCast, Werewolf.GameEngine","PlayerName":"ctsk","GameId":"rox-319","TimeStamp":"2021-07-21T21:38:53.1860427Z"},{"__type":"Werewolf.GameEngine.Phases.Night.NightStartedEvent, Werewolf.GameEngine","NightNumber":2,"PhaseLength":0,"GameId":"rox-319","TimeStamp":"2021-07-21T21:39:06.2030885Z"},{"__type":"Werewolf.GameEngine.Phases.NoPlayerLynched, Werewolf.GameEngine","GameId":"rox-319","TimeStamp":"2021-07-21T21:39:06.2031177Z"},{"__type":"Werewolf.GameEngine.Roles.ValidPrimaryNightTargetsShown, Werewolf.GameEngine","PlayerWithRole":"ImTownSRSLY","PlayerNames":["SnapDragon","ctsk","ShaneMcC","Phyton","SavvySteve","Ellie","NicolBolas"],"ActionName":"Kill","Message":"The wolfpack have 1 kill tonight","DetailedDescription":null,"RoleOptions":null,"GameId":"rox-319","TimeStamp":"2021-07-21T21:39:06.2031706Z"},{"__type":"Werewolf.GameEngine.Roles.ValidPrimaryNightTargetsShown, Werewolf.GameEngine","PlayerWithRole":"Rox","PlayerNames":["SnapDragon","ctsk","ImTownSRSLY","ShaneMcC","Phyton","SavvySteve","laser","Ellie","NicolBolas"],"ActionName":"Recruit","Message":null,"DetailedDescription":null,"RoleOptions":null,"GameId":"rox-319","TimeStamp":"2021-07-21T21:39:06.2032054Z"},{"__type":"Werewolf.GameEngine.Roles.ValidPrimaryNightTargetsShown, Werewolf.GameEngine","PlayerWithRole":"SavvySteve","PlayerNames":["SnapDragon","ctsk","ImTownSRSLY","ShaneMcC","Phyton","laser","Ellie","NicolBolas"],"ActionName":"Check","Message":null,"DetailedDescription":null,"RoleOptions":null,"GameId":"rox-319","TimeStamp":"2021-07-21T21:39:06.2032381Z"},{"__type":"Werewolf.GameEngine.Roles.ValidPrimaryNightTargetsShown, Werewolf.GameEngine","PlayerWithRole":"laser","PlayerNames":["SnapDragon","ctsk","ImTownSRSLY","ShaneMcC","Phyton","SavvySteve","Ellie","NicolBolas"],"ActionName":"Mark","Message":null,"DetailedDescription":null,"RoleOptions":null,"GameId":"rox-319","TimeStamp":"2021-07-21T21:39:06.2032475Z"},{"__type":"Werewolf.GameEngine.Roles.ValidPrimaryNightTargetsShown, Werewolf.GameEngine","PlayerWithRole":"Ramen_Fluffy","PlayerNames":["SnapDragon","ctsk","ImTownSRSLY","ShaneMcC","SavvySteve","laser","Ellie","NicolBolas"],"ActionName":"Protect","Message":null,"DetailedDescription":null,"RoleOptions":null,"GameId":"rox-319","TimeStamp":"2021-07-21T21:39:06.2032502Z"},{"__type":"Werewolf.GameEngine.Roles.NightTargetChosenEvent, Werewolf.GameEngine","Confirmation":"Tonight you will weave a spell for $ctsk","AlliesConfirmation":null,"Allies":null,"PlayerWithRole":"SnapDragon","Role":"Spell Weaver","Target":"ctsk","GameId":"rox-319","TimeStamp":"2021-07-21T21:39:13.6792714Z"},{"__type":"Werewolf.GameEngine.Chatting.WerewolfNightMessageEvent, Werewolf.GameEngine","PlayerName":"laser","Message":"so that's good","Recipients":["ImTownSRSLY","laser"],"Eavesdroppers":[],"GameId":"rox-319","TimeStamp":"2021-07-21T21:39:16.0247934Z"},{"__type":"Werewolf.GameEngine.Roles.NightTargetChosenEvent, Werewolf.GameEngine","Confirmation":"Tonight you will ascertain whether or not $Ellie is capable of murder","AlliesConfirmation":null,"Allies":null,"PlayerWithRole":"SavvySteve","Role":"Adjudicator","Target":"Ellie","GameId":"rox-319","TimeStamp":"2021-07-21T21:39:16.233771Z"},{"__type":"Werewolf.GameEngine.Chatting.WerewolfNightMessageEvent, Werewolf.GameEngine","PlayerName":"laser","Message":"Phy may be self-prot","Recipients":["ImTownSRSLY","laser"],"Eavesdroppers":[],"GameId":"rox-319","TimeStamp":"2021-07-21T21:39:20.7198223Z"},{"__type":"Werewolf.GameEngine.Chatting.WerewolfNightMessageEvent, Werewolf.GameEngine","PlayerName":"laser","Message":"and mason leader is dead","Recipients":["ImTownSRSLY","laser"],"Eavesdroppers":[],"GameId":"rox-319","TimeStamp":"2021-07-21T21:39:23.5907439Z"},{"__type":"Werewolf.GameEngine.Phases.Night.WerewolfVoteEvent, Werewolf.GameEngine","Werewolf":"ImTownSRSLY","Target":"Phyton","Recipients":["ImTownSRSLY","laser"],"MaxKillCount":1,"ThisKill":1,"GameId":"rox-319","TimeStamp":"2021-07-21T21:39:28.4105441Z"},{"__type":"Werewolf.GameEngine.Roles.NightTargetChosenEvent, Werewolf.GameEngine","Confirmation":"Tonight you will mark $Ellie with wolf blood","AlliesConfirmation":"Tonight $laser will mark $Ellie with wolf blood","Allies":["ImTownSRSLY"],"PlayerWithRole":"laser","Role":"Bloodletter","Target":"Ellie","GameId":"rox-319","TimeStamp":"2021-07-21T21:39:30.5933249Z"},{"__type":"Werewolf.GameEngine.Chatting.WerewolfNightMessageEvent, Werewolf.GameEngine","PlayerName":"ImTownSRSLY","Message":"Agreeed","Recipients":["ImTownSRSLY","laser"],"Eavesdroppers":[],"GameId":"rox-319","TimeStamp":"2021-07-21T21:39:35.5649949Z"},{"__type":"Werewolf.GameEngine.Chatting.WerewolfNightMessageEvent, Werewolf.GameEngine","PlayerName":"ImTownSRSLY","Message":"I feel rox went for one of usss","Recipients":["ImTownSRSLY","laser"],"Eavesdroppers":[],"GameId":"rox-319","TimeStamp":"2021-07-21T21:39:41.587391Z"},{"__type":"Werewolf.GameEngine.Chatting.WerewolfNightMessageEvent, Werewolf.GameEngine","PlayerName":"laser","Message":"yeah","Recipients":["ImTownSRSLY","laser"],"Eavesdroppers":[],"GameId":"rox-319","TimeStamp":"2021-07-21T21:39:46.0093593Z"},{"__type":"Werewolf.GameEngine.Phases.Day.DayStartsSoonWarningGiven, Werewolf.GameEngine","FlavourText":"The darkness yields...","GameId":"rox-319","TimeStamp":"2021-07-21T21:40:36.6880819Z"},{"__type":"Werewolf.GameEngine.Roles.Werewolves.Bloodletter.PlayerMarkedByBloodletter, Werewolf.GameEngine","PlayerWithRole":"laser","Target":"Ellie","NightNumber":2,"GameId":"rox-319","TimeStamp":"2021-07-21T21:41:06.0776925Z"},{"__type":"Werewolf.GameEngine.Items.EnchantedScrollAllocated, Werewolf.GameEngine","PlayerName":"ctsk","ItemId":"c42747f5-5b08-41e9-ba8c-9d4959c2b7b4","ItemOptions":["amplify-self-silence-neighbours","silence-self-amplify-neighbours"],"GameId":"rox-319","TimeStamp":"2021-07-21T21:41:06.0776995Z"},{"__type":"Werewolf.GameEngine.Roles.MorningReportShown, Werewolf.GameEngine","Message":"$Ellie is capable of murder","PlayerWithRole":"SavvySteve","Role":"Adjudicator","GameId":"rox-319","TimeStamp":"2021-07-21T21:41:06.0778563Z"},{"__type":"Werewolf.GameEngine.Phases.Night.PlayerKilledEvent, Werewolf.GameEngine","PlayerName":"Phyton","CauseOfDeath":"Werewolf","GameId":"rox-319","TimeStamp":"2021-07-21T21:41:06.077899Z"},{"__type":"Werewolf.GameEngine.Phases.Day.DayStartedEvent, Werewolf.GameEngine","DayNumber":3,"PhaseLength":0,"DiscussionLength":0,"GameId":"rox-319","TimeStamp":"2021-07-21T21:41:06.0779078Z"},{"__type":"Werewolf.GameEngine.Chatting.GhostMessageEvent, Werewolf.GameEngine","PlayerName":"Rox","Message":"Laser","Recipients":["Ramen_Fluffy","Rox","Phyton"],"GameId":"rox-319","TimeStamp":"2021-07-21T21:41:13.9919257Z"},{"__type":"Werewolf.GameEngine.Chatting.VillageMessageEvent, Werewolf.GameEngine","PlayerName":"ShaneMcC","Message":"HOW VERY DARE YOU","GameId":"rox-319","TimeStamp":"2021-07-21T21:41:15.504147Z"},{"__type":"Werewolf.GameEngine.Chatting.GhostMessageEvent, Werewolf.GameEngine","PlayerName":"Rox","Message":"👀","Recipients":["Ramen_Fluffy","Rox","Phyton"],"GameId":"rox-319","TimeStamp":"2021-07-21T21:41:27.5000698Z"},{"__type":"Werewolf.GameEngine.Phases.Day.VillageNominationsOpenedEvent, Werewolf.GameEngine","TimeLeft":0,"GameId":"rox-319","TimeStamp":"2021-07-21T21:41:36.1775966Z"},{"__type":"Werewolf.GameEngine.Phases.Day.NoLynchOptionAvailable, Werewolf.GameEngine","GameId":"rox-319","TimeStamp":"2021-07-21T21:41:36.1775988Z"},{"__type":"Werewolf.GameEngine.Phases.Day.SkipDayOptionAvailable, Werewolf.GameEngine","GameId":"rox-319","TimeStamp":"2021-07-21T21:41:36.1775995Z"},{"__type":"Werewolf.GameEngine.Chatting.GhostMessageEvent, Werewolf.GameEngine","PlayerName":"Rox","Message":"Adjudicator ","Recipients":["Ramen_Fluffy","Rox","Phyton"],"GameId":"rox-319","TimeStamp":"2021-07-21T21:41:40.5949866Z"},{"__type":"Werewolf.GameEngine.Phases.Day.VillageNominationEvent, Werewolf.GameEngine","PlayerName":"SavvySteve","Target":"Ellie","GameId":"rox-319","TimeStamp":"2021-07-21T21:41:43.5326666Z"},{"__type":"Werewolf.GameEngine.Phases.Day.VillageNominationEvent, Werewolf.GameEngine","PlayerName":"ShaneMcC","Target":"Ellie","GameId":"rox-319","TimeStamp":"2021-07-21T21:41:45.3664472Z"},{"__type":"Werewolf.GameEngine.Phases.Day.VillageNominationEvent, Werewolf.GameEngine","PlayerName":"SnapDragon","Target":"Ellie","GameId":"rox-319","TimeStamp":"2021-07-21T21:41:46.7236648Z"},{"__type":"Werewolf.GameEngine.Phases.Day.VillageNominationEvent, Werewolf.GameEngine","PlayerName":"ImTownSRSLY","Target":"Ellie","GameId":"rox-319","TimeStamp":"2021-07-21T21:41:53.1789358Z"},{"__type":"Werewolf.GameEngine.Phases.Day.VillageNominationEvent, Werewolf.GameEngine","PlayerName":"NicolBolas","Target":"Ellie","GameId":"rox-319","TimeStamp":"2021-07-21T21:41:54.8335105Z"},{"__type":"Werewolf.GameEngine.Chatting.GhostMessageEvent, Werewolf.GameEngine","PlayerName":"Rox","Message":"Dang they were my first choice for recruit but went laser","Recipients":["Ramen_Fluffy","Rox","Phyton"],"GameId":"rox-319","TimeStamp":"2021-07-21T21:41:56.9950312Z"},{"__type":"Werewolf.GameEngine.Chatting.GhostMessageEvent, Werewolf.GameEngine","PlayerName":"Rox","Message":"Woah","Recipients":["Ramen_Fluffy","Rox","Phyton"],"GameId":"rox-319","TimeStamp":"2021-07-21T21:42:15.8923556Z"},{"__type":"Werewolf.GameEngine.Chatting.GhostMessageEvent, Werewolf.GameEngine","PlayerName":"Ramen_Fluffy","Message":"oof","Recipients":["Ramen_Fluffy","Rox","Phyton"],"GameId":"rox-319","TimeStamp":"2021-07-21T21:42:16.6035751Z"},{"__type":"Werewolf.GameEngine.Chatting.VillageMessageEvent, Werewolf.GameEngine","PlayerName":"laser","Message":"do you have a counter claim Ellie?","GameId":"rox-319","TimeStamp":"2021-07-21T21:42:23.5264274Z"},{"__type":"Werewolf.GameEngine.Phases.Day.VillageNominationEvent, Werewolf.GameEngine","PlayerName":"laser","Target":"Ellie","GameId":"rox-319","TimeStamp":"2021-07-21T21:42:31.8767081Z"},{"__type":"Werewolf.GameEngine.Chatting.GhostMessageEvent, Werewolf.GameEngine","PlayerName":"Rox","Message":"Yeah nah","Recipients":["Ramen_Fluffy","Rox","Phyton"],"GameId":"rox-319","TimeStamp":"2021-07-21T21:42:48.438629Z"},{"__type":"Werewolf.GameEngine.Phases.Day.VillageNominationEvent, Werewolf.GameEngine","PlayerName":"ctsk","Target":"Ellie","GameId":"rox-319","TimeStamp":"2021-07-21T21:42:56.1646523Z"},{"__type":"Werewolf.GameEngine.Chatting.VillageMessageEvent, Werewolf.GameEngine","PlayerName":"ctsk","Message":"Check Nico pls","GameId":"rox-319","TimeStamp":"2021-07-21T21:43:04.9792733Z"},{"__type":"Werewolf.GameEngine.Phases.VoteForSkipDayCast, Werewolf.GameEngine","PlayerName":"SavvySteve","GameId":"rox-319","TimeStamp":"2021-07-21T21:43:08.9134119Z"},{"__type":"Werewolf.GameEngine.Chatting.GhostMessageEvent, Werewolf.GameEngine","PlayerName":"Rox","Message":"Very subtle","Recipients":["Ramen_Fluffy","Rox","Phyton"],"GameId":"rox-319","TimeStamp":"2021-07-21T21:43:12.1935609Z"},{"__type":"Werewolf.GameEngine.Phases.VoteForSkipDayCast, Werewolf.GameEngine","PlayerName":"SnapDragon","GameId":"rox-319","TimeStamp":"2021-07-21T21:43:49.8769793Z"},{"__type":"Werewolf.GameEngine.Phases.VoteForSkipDayCast, Werewolf.GameEngine","PlayerName":"ImTownSRSLY","GameId":"rox-319","TimeStamp":"2021-07-21T21:44:01.502995Z"},{"__type":"Werewolf.GameEngine.Phases.VoteForNoLynchCast, Werewolf.GameEngine","PlayerName":"Ellie","GameId":"rox-319","TimeStamp":"2021-07-21T21:44:02.2831343Z"},{"__type":"Werewolf.GameEngine.Chatting.GhostMessageEvent, Werewolf.GameEngine","PlayerName":"Phyton","Message":"Laser huh?","Recipients":["Ramen_Fluffy","Rox","Phyton"],"GameId":"rox-319","TimeStamp":"2021-07-21T21:44:11.1694836Z"},{"__type":"Werewolf.GameEngine.Chatting.GhostMessageEvent, Werewolf.GameEngine","PlayerName":"Rox","Message":"Yeah","Recipients":["Ramen_Fluffy","Rox","Phyton"],"GameId":"rox-319","TimeStamp":"2021-07-21T21:44:14.3297688Z"},{"__type":"Werewolf.GameEngine.Chatting.GhostMessageEvent, Werewolf.GameEngine","PlayerName":"Ramen_Fluffy","Message":"yes","Recipients":["Ramen_Fluffy","Rox","Phyton"],"GameId":"rox-319","TimeStamp":"2021-07-21T21:44:15.3167974Z"},{"__type":"Werewolf.GameEngine.Chatting.GhostMessageEvent, Werewolf.GameEngine","PlayerName":"Phyton","Message":"Sad sad","Recipients":["Ramen_Fluffy","Rox","Phyton"],"GameId":"rox-319","TimeStamp":"2021-07-21T21:44:16.3784376Z"},{"__type":"Werewolf.GameEngine.Chatting.GhostMessageEvent, Werewolf.GameEngine","PlayerName":"Phyton","Message":":(","Recipients":["Ramen_Fluffy","Rox","Phyton"],"GameId":"rox-319","TimeStamp":"2021-07-21T21:44:17.7694269Z"},{"__type":"Werewolf.GameEngine.Chatting.GhostMessageEvent, Werewolf.GameEngine","PlayerName":"Ramen_Fluffy","Message":"What were you phy?","Recipients":["Ramen_Fluffy","Rox","Phyton"],"GameId":"rox-319","TimeStamp":"2021-07-21T21:44:22.0163336Z"},{"__type":"Werewolf.GameEngine.Chatting.GhostMessageEvent, Werewolf.GameEngine","PlayerName":"Phyton","Message":"I am the Witch","Recipients":["Ramen_Fluffy","Rox","Phyton"],"GameId":"rox-319","TimeStamp":"2021-07-21T21:44:44.3193055Z"},{"__type":"Werewolf.GameEngine.Chatting.GhostMessageEvent, Werewolf.GameEngine","PlayerName":"Rox","Message":":0","Recipients":["Ramen_Fluffy","Rox","Phyton"],"GameId":"rox-319","TimeStamp":"2021-07-21T21:44:48.3924958Z"},{"__type":"Werewolf.GameEngine.Chatting.GhostMessageEvent, Werewolf.GameEngine","PlayerName":"Rox","Message":"Wow","Recipients":["Ramen_Fluffy","Rox","Phyton"],"GameId":"rox-319","TimeStamp":"2021-07-21T21:44:52.9124639Z"},{"__type":"Werewolf.GameEngine.Chatting.GhostMessageEvent, Werewolf.GameEngine","PlayerName":"Ramen_Fluffy","Message":"spell weaveR?","Recipients":["Ramen_Fluffy","Rox","Phyton"],"GameId":"rox-319","TimeStamp":"2021-07-21T21:44:54.9938824Z"},{"__type":"Werewolf.GameEngine.Chatting.GhostMessageEvent, Werewolf.GameEngine","PlayerName":"Rox","Message":"Snap just claimed spell weaver","Recipients":["Ramen_Fluffy","Rox","Phyton"],"GameId":"rox-319","TimeStamp":"2021-07-21T21:45:03.8249671Z"},{"__type":"Werewolf.GameEngine.Chatting.VillageMessageEvent, Werewolf.GameEngine","PlayerName":"SnapDragon","Message":"Yeet yeet yeet your spells gently in the vilalge","GameId":"rox-319","TimeStamp":"2021-07-21T21:45:34.3842874Z"},{"__type":"Werewolf.GameEngine.Phases.Night.NightStartsSoonWarningGiven, Werewolf.GameEngine","FlavourText":"Night is almost upon us...","GameId":"rox-319","TimeStamp":"2021-07-21T21:45:36.2474861Z"},{"__type":"Werewolf.GameEngine.Chatting.GhostMessageEvent, Werewolf.GameEngine","PlayerName":"Ramen_Fluffy","Message":"Didn't hear that part, thought phy was spell weaver for being \"witch\"","Recipients":["Ramen_Fluffy","Rox","Phyton"],"GameId":"rox-319","TimeStamp":"2021-07-21T21:45:57.4795906Z"},{"__type":"Werewolf.GameEngine.Phases.Night.NightStartedEvent, Werewolf.GameEngine","NightNumber":3,"PhaseLength":0,"GameId":"rox-319","TimeStamp":"2021-07-21T21:46:06.1658192Z"},{"__type":"Werewolf.GameEngine.Phases.Day.PlayerLynchedEvent, Werewolf.GameEngine","PlayerName":"Ellie","Message":"was stoned to death by the village","GameId":"rox-319","TimeStamp":"2021-07-21T21:46:06.1661413Z"},{"__type":"Werewolf.GameEngine.Roles.ValidPrimaryNightTargetsShown, Werewolf.GameEngine","PlayerWithRole":"ImTownSRSLY","PlayerNames":["SnapDragon","ctsk","ShaneMcC","SavvySteve","NicolBolas"],"ActionName":"Kill","Message":"The wolfpack have 1 kill tonight","DetailedDescription":null,"RoleOptions":null,"GameId":"rox-319","TimeStamp":"2021-07-21T21:46:06.1661851Z"},{"__type":"Werewolf.GameEngine.Items.ItemAvailable, Werewolf.GameEngine","ItemIndex":0,"ItemName":"Enchanted Scroll","Description":null,"DetailedDescription":["A scroll that seems to exude magic around it. There are incantations inscribed on it that you may choose to follow","This scroll may only be used once","1) Amplify your own vote, making it count for 2 tomorrow. Silence your neighbours' votes, making them both count for 0 tomorrow","2) Silence your own vote, making it count for 0 tomorrow. Amplify your neighbours' votes, making them both count for 2 tomorrow"],"PlayerWithItem":"ctsk","ActionName":"choose","PlayerNames":[],"ItemOptions":[{"__type":"Werewolf.GameEngine.Items.ItemUseOption, Werewolf.GameEngine","IconName":"Moderator","ActionName":"amplify-self-silence-neighbours","Description":"Amplify self","Available":true},{"__type":"Werewolf.GameEngine.Items.ItemUseOption, Werewolf.GameEngine","IconName":"Moderator","ActionName":"silence-self-amplify-neighbours","Description":"Silence self","Available":true}],"GameId":"rox-319","TimeStamp":"2021-07-21T21:46:06.1739826Z"},{"__type":"Werewolf.GameEngine.Roles.ValidPrimaryNightTargetsShown, Werewolf.GameEngine","PlayerWithRole":"Rox","PlayerNames":["SnapDragon","ctsk","ImTownSRSLY","ShaneMcC","SavvySteve","laser","NicolBolas"],"ActionName":"Recruit","Message":null,"DetailedDescription":null,"RoleOptions":null,"GameId":"rox-319","TimeStamp":"2021-07-21T21:46:06.1744322Z"},{"__type":"Werewolf.GameEngine.Roles.ValidPrimaryNightTargetsShown, Werewolf.GameEngine","PlayerWithRole":"SavvySteve","PlayerNames":["SnapDragon","ctsk","ImTownSRSLY","ShaneMcC","laser","NicolBolas"],"ActionName":"Check","Message":null,"DetailedDescription":null,"RoleOptions":null,"GameId":"rox-319","TimeStamp":"2021-07-21T21:46:06.1744544Z"},{"__type":"Werewolf.GameEngine.Roles.ValidPrimaryNightTargetsShown, Werewolf.GameEngine","PlayerWithRole":"laser","PlayerNames":["SnapDragon","ctsk","ImTownSRSLY","ShaneMcC","SavvySteve","Ellie","NicolBolas"],"ActionName":"Mark","Message":null,"DetailedDescription":null,"RoleOptions":null,"GameId":"rox-319","TimeStamp":"2021-07-21T21:46:06.1744637Z"},{"__type":"Werewolf.GameEngine.Roles.ValidPrimaryNightTargetsShown, Werewolf.GameEngine","PlayerWithRole":"Ramen_Fluffy","PlayerNames":["SnapDragon","ctsk","ImTownSRSLY","ShaneMcC","SavvySteve","laser","NicolBolas"],"ActionName":"Protect","Message":null,"DetailedDescription":null,"RoleOptions":null,"GameId":"rox-319","TimeStamp":"2021-07-21T21:46:06.1744678Z"},{"__type":"Werewolf.GameEngine.Chatting.GhostMessageEvent, Werewolf.GameEngine","PlayerName":"Rox","Message":"Oh snap said it after","Recipients":["Ramen_Fluffy","Rox","Phyton","Ellie"],"GameId":"rox-319","TimeStamp":"2021-07-21T21:46:06.9947833Z"},{"__type":"Werewolf.GameEngine.Roles.NightTargetChosenEvent, Werewolf.GameEngine","Confirmation":"Tonight you will weave a spell for $ImTownSRSLY","AlliesConfirmation":null,"Allies":null,"PlayerWithRole":"SnapDragon","Role":"Spell Weaver","Target":"ImTownSRSLY","GameId":"rox-319","TimeStamp":"2021-07-21T21:46:10.4002803Z"},{"__type":"Werewolf.GameEngine.Roles.NightTargetChosenEvent, Werewolf.GameEngine","Confirmation":"Tonight you will ascertain whether or not $ctsk is capable of murder","AlliesConfirmation":null,"Allies":null,"PlayerWithRole":"SavvySteve","Role":"Adjudicator","Target":"ctsk","GameId":"rox-319","TimeStamp":"2021-07-21T21:46:16.2804408Z"},{"__type":"Werewolf.GameEngine.Chatting.WerewolfNightMessageEvent, Werewolf.GameEngine","PlayerName":"laser","Message":"what does the spell weaver mean for us/","Recipients":["ImTownSRSLY","laser"],"Eavesdroppers":[],"GameId":"rox-319","TimeStamp":"2021-07-21T21:46:18.1771036Z"},{"__type":"Werewolf.GameEngine.Chatting.GhostMessageEvent, Werewolf.GameEngine","PlayerName":"Phyton","Message":"He too serious","Recipients":["Ramen_Fluffy","Rox","Phyton","Ellie"],"GameId":"rox-319","TimeStamp":"2021-07-21T21:46:22.440923Z"},{"__type":"Werewolf.GameEngine.Chatting.WerewolfNightMessageEvent, Werewolf.GameEngine","PlayerName":"laser","Message":"presumably we can receive as per usual?","Recipients":["ImTownSRSLY","laser"],"Eavesdroppers":[],"GameId":"rox-319","TimeStamp":"2021-07-21T21:46:23.7947439Z"},{"__type":"Werewolf.GameEngine.Chatting.GhostMessageEvent, Werewolf.GameEngine","PlayerName":"Rox","Message":"I suck hard in my own games","Recipients":["Ramen_Fluffy","Rox","Phyton","Ellie"],"GameId":"rox-319","TimeStamp":"2021-07-21T21:46:24.0325845Z"},{"__type":"Werewolf.GameEngine.Chatting.WerewolfNightMessageEvent, Werewolf.GameEngine","PlayerName":"ImTownSRSLY","Message":"someone with additional votes","Recipients":["ImTownSRSLY","laser"],"Eavesdroppers":[],"GameId":"rox-319","TimeStamp":"2021-07-21T21:46:26.3784823Z"},{"__type":"Werewolf.GameEngine.Chatting.WerewolfNightMessageEvent, Werewolf.GameEngine","PlayerName":"laser","Message":"or does it out us?","Recipients":["ImTownSRSLY","laser"],"Eavesdroppers":[],"GameId":"rox-319","TimeStamp":"2021-07-21T21:46:27.2456092Z"},{"__type":"Werewolf.GameEngine.Chatting.WerewolfNightMessageEvent, Werewolf.GameEngine","PlayerName":"laser","Message":"okay","Recipients":["ImTownSRSLY","laser"],"Eavesdroppers":[],"GameId":"rox-319","TimeStamp":"2021-07-21T21:46:29.3538061Z"},{"__type":"Werewolf.GameEngine.Chatting.WerewolfNightMessageEvent, Werewolf.GameEngine","PlayerName":"ImTownSRSLY","Message":"kill savvy or not?","Recipients":["ImTownSRSLY","laser"],"Eavesdroppers":[],"GameId":"rox-319","TimeStamp":"2021-07-21T21:46:35.590034Z"},{"__type":"Werewolf.GameEngine.Chatting.WerewolfNightMessageEvent, Werewolf.GameEngine","PlayerName":"laser","Message":"yeah i think so","Recipients":["ImTownSRSLY","laser"],"Eavesdroppers":[],"GameId":"rox-319","TimeStamp":"2021-07-21T21:46:38.6522597Z"},{"__type":"Werewolf.GameEngine.Chatting.WerewolfNightMessageEvent, Werewolf.GameEngine","PlayerName":"ImTownSRSLY","Message":"we think phy is prot right","Recipients":["ImTownSRSLY","laser"],"Eavesdroppers":[],"GameId":"rox-319","TimeStamp":"2021-07-21T21:46:38.9476486Z"},{"__type":"Werewolf.GameEngine.Chatting.WerewolfNightMessageEvent, Werewolf.GameEngine","PlayerName":"laser","Message":"no prot","Recipients":["ImTownSRSLY","laser"],"Eavesdroppers":[],"GameId":"rox-319","TimeStamp":"2021-07-21T21:46:39.4930058Z"},{"__type":"Werewolf.GameEngine.Chatting.GhostMessageEvent, Werewolf.GameEngine","PlayerName":"Rox","Message":"YES THE AXARA COVER","Recipients":["Ramen_Fluffy","Rox","Phyton","Ellie"],"GameId":"rox-319","TimeStamp":"2021-07-21T21:46:41.2322565Z"},{"__type":"Werewolf.GameEngine.Roles.NightTargetChosenEvent, Werewolf.GameEngine","Confirmation":"Tonight you will mark $NicolBolas with wolf blood","AlliesConfirmation":"Tonight $laser will mark $NicolBolas with wolf blood","Allies":["ImTownSRSLY"],"PlayerWithRole":"laser","Role":"Bloodletter","Target":"NicolBolas","GameId":"rox-319","TimeStamp":"2021-07-21T21:46:43.4228915Z"},{"__type":"Werewolf.GameEngine.Chatting.GhostMessageEvent, Werewolf.GameEngine","PlayerName":"Rox","Message":"AAAAA","Recipients":["Ramen_Fluffy","Rox","Phyton","Ellie"],"GameId":"rox-319","TimeStamp":"2021-07-21T21:46:46.2624805Z"},{"__type":"Werewolf.GameEngine.Chatting.WerewolfNightMessageEvent, Werewolf.GameEngine","PlayerName":"ImTownSRSLY","Message":"but if we kill savvy none of us can claim prot","Recipients":["ImTownSRSLY","laser"],"Eavesdroppers":[],"GameId":"rox-319","TimeStamp":"2021-07-21T21:46:51.9771911Z"},{"__type":"Werewolf.GameEngine.Chatting.WerewolfNightMessageEvent, Werewolf.GameEngine","PlayerName":"ImTownSRSLY","Message":"so I kinda dont wanna kill them","Recipients":["ImTownSRSLY","laser"],"Eavesdroppers":[],"GameId":"rox-319","TimeStamp":"2021-07-21T21:46:56.4483688Z"},{"__type":"Werewolf.GameEngine.Chatting.WerewolfNightMessageEvent, Werewolf.GameEngine","PlayerName":"ImTownSRSLY","Message":"one of us can claim prot","Recipients":["ImTownSRSLY","laser"],"Eavesdroppers":[],"GameId":"rox-319","TimeStamp":"2021-07-21T21:47:02.4890354Z"},{"__type":"Werewolf.GameEngine.Chatting.GhostMessageEvent, Werewolf.GameEngine","PlayerName":"Phyton","Message":"Don't worry","Recipients":["Ramen_Fluffy","Rox","Phyton","Ellie"],"GameId":"rox-319","TimeStamp":"2021-07-21T21:47:13.7802565Z"},{"__type":"Werewolf.GameEngine.Chatting.WerewolfNightMessageEvent, Werewolf.GameEngine","PlayerName":"laser","Message":"we can claim we protected Snap instead or something","Recipients":["ImTownSRSLY","laser"],"Eavesdroppers":[],"GameId":"rox-319","TimeStamp":"2021-07-21T21:47:14.4403958Z"},{"__type":"Werewolf.GameEngine.Chatting.WerewolfNightMessageEvent, Werewolf.GameEngine","PlayerName":"laser","Message":"I'd rather get rid of power roles","Recipients":["ImTownSRSLY","laser"],"Eavesdroppers":[],"GameId":"rox-319","TimeStamp":"2021-07-21T21:47:18.3204986Z"},{"__type":"Werewolf.GameEngine.Phases.Night.WerewolfVoteEvent, Werewolf.GameEngine","Werewolf":"ImTownSRSLY","Target":"SavvySteve","Recipients":["ImTownSRSLY","laser"],"MaxKillCount":1,"ThisKill":1,"GameId":"rox-319","TimeStamp":"2021-07-21T21:47:22.3974461Z"},{"__type":"Werewolf.GameEngine.Chatting.WerewolfNightMessageEvent, Werewolf.GameEngine","PlayerName":"ImTownSRSLY","Message":"kk","Recipients":["ImTownSRSLY","laser"],"Eavesdroppers":[],"GameId":"rox-319","TimeStamp":"2021-07-21T21:47:24.3292529Z"},{"__type":"Werewolf.GameEngine.Phases.Day.DayStartsSoonWarningGiven, Werewolf.GameEngine","FlavourText":"It will soon be day...","GameId":"rox-319","TimeStamp":"2021-07-21T21:47:36.1869207Z"},{"__type":"Werewolf.GameEngine.Items.ItemNightOptionChosen, Werewolf.GameEngine","Bearer":"ctsk","Option":"amplify-self-silence-neighbours","ItemId":"c42747f5-5b08-41e9-ba8c-9d4959c2b7b4","ItemName":"Enchanted Scroll","Confirmation":"You will use the scroll to Amplify your own vote tomorrow and Silence both your neighbours. $$","GameId":"rox-319","TimeStamp":"2021-07-21T21:47:38.2131798Z"},{"__type":"Werewolf.GameEngine.Roles.Werewolves.Bloodletter.PlayerMarkedByBloodletter, Werewolf.GameEngine","PlayerWithRole":"laser","Target":"NicolBolas","NightNumber":3,"GameId":"rox-319","TimeStamp":"2021-07-21T21:48:06.4434752Z"},{"__type":"Werewolf.GameEngine.Items.EnchantedScrollAllocated, Werewolf.GameEngine","PlayerName":"ImTownSRSLY","ItemId":"b4273524-5150-4c53-84a9-6e3e21733c28","ItemOptions":["agitate","reveal-executed-role"],"GameId":"rox-319","TimeStamp":"2021-07-21T21:48:06.4434812Z"},{"__type":"Werewolf.GameEngine.Roles.MorningReportShown, Werewolf.GameEngine","Message":"$ctsk is not a killer","PlayerWithRole":"SavvySteve","Role":"Adjudicator","GameId":"rox-319","TimeStamp":"2021-07-21T21:48:06.4435223Z"},{"__type":"Werewolf.GameEngine.Items.ItemConsumed, Werewolf.GameEngine","ItemId":"c42747f5-5b08-41e9-ba8c-9d4959c2b7b4","PlayerName":"ctsk","GameId":"rox-319","TimeStamp":"2021-07-21T21:48:06.4437412Z"},{"__type":"Werewolf.GameEngine.Phases.Night.PlayerKilledEvent, Werewolf.GameEngine","PlayerName":"SavvySteve","CauseOfDeath":"Werewolf","GameId":"rox-319","TimeStamp":"2021-07-21T21:48:06.4439545Z"},{"__type":"Werewolf.GameEngine.Phases.Day.DayStartedEvent, Werewolf.GameEngine","DayNumber":4,"PhaseLength":0,"DiscussionLength":0,"GameId":"rox-319","TimeStamp":"2021-07-21T21:48:06.4439645Z"},{"__type":"Werewolf.GameEngine.Phases.PlayersVoteAmplified, Werewolf.GameEngine","Target":"ctsk","GameId":"rox-319","TimeStamp":"2021-07-21T21:48:06.4480891Z"},{"__type":"Werewolf.GameEngine.Phases.PlayersVoteSilenced, Werewolf.GameEngine","Target":"SavvySteve","GameId":"rox-319","TimeStamp":"2021-07-21T21:48:06.4481446Z"},{"__type":"Werewolf.GameEngine.Phases.PlayersVoteSilenced, Werewolf.GameEngine","Target":"laser","GameId":"rox-319","TimeStamp":"2021-07-21T21:48:06.4481543Z"},{"__type":"Werewolf.GameEngine.Chatting.GhostMessageEvent, Werewolf.GameEngine","PlayerName":"Rox","Message":"I made poor decisions","Recipients":["Ramen_Fluffy","Rox","Phyton","Ellie","SavvySteve"],"GameId":"rox-319","TimeStamp":"2021-07-21T21:48:14.9367548Z"},{"__type":"Werewolf.GameEngine.Chatting.GhostMessageEvent, Werewolf.GameEngine","PlayerName":"SavvySteve","Message":"F","Recipients":["Ramen_Fluffy","Rox","Phyton","Ellie","SavvySteve"],"GameId":"rox-319","TimeStamp":"2021-07-21T21:48:17.9952099Z"},{"__type":"Werewolf.GameEngine.Chatting.GhostMessageEvent, Werewolf.GameEngine","PlayerName":"Rox","Message":"Laser is a wolf","Recipients":["Ramen_Fluffy","Rox","Phyton","Ellie","SavvySteve"],"GameId":"rox-319","TimeStamp":"2021-07-21T21:48:23.7042164Z"},{"__type":"Werewolf.GameEngine.Chatting.GhostMessageEvent, Werewolf.GameEngine","PlayerName":"SavvySteve","Message":"Oof","Recipients":["Ramen_Fluffy","Rox","Phyton","Ellie","SavvySteve"],"GameId":"rox-319","TimeStamp":"2021-07-21T21:48:27.7242825Z"},{"__type":"Werewolf.GameEngine.Phases.Day.VillageNominationsOpenedEvent, Werewolf.GameEngine","TimeLeft":0,"GameId":"rox-319","TimeStamp":"2021-07-21T21:48:36.3724799Z"},{"__type":"Werewolf.GameEngine.Phases.Day.NoLynchOptionAvailable, Werewolf.GameEngine","GameId":"rox-319","TimeStamp":"2021-07-21T21:48:36.372482Z"},{"__type":"Werewolf.GameEngine.Phases.Day.SkipDayOptionAvailable, Werewolf.GameEngine","GameId":"rox-319","TimeStamp":"2021-07-21T21:48:36.3724827Z"},{"__type":"Werewolf.GameEngine.Chatting.GhostMessageEvent, Werewolf.GameEngine","PlayerName":"SavvySteve","Message":"ctsk can't kill","Recipients":["Ramen_Fluffy","Rox","Phyton","Ellie","SavvySteve"],"GameId":"rox-319","TimeStamp":"2021-07-21T21:48:44.9027438Z"},{"__type":"Werewolf.GameEngine.Chatting.GhostMessageEvent, Werewolf.GameEngine","PlayerName":"Rox","Message":"Ramen is prot","Recipients":["Ramen_Fluffy","Rox","Phyton","Ellie","SavvySteve"],"GameId":"rox-319","TimeStamp":"2021-07-21T21:48:45.3291184Z"},{"__type":"Werewolf.GameEngine.Chatting.GhostMessageEvent, Werewolf.GameEngine","PlayerName":"Ramen_Fluffy","Message":"prot died","Recipients":["Ramen_Fluffy","Rox","Phyton","Ellie","SavvySteve"],"GameId":"rox-319","TimeStamp":"2021-07-21T21:48:48.927995Z"},{"__type":"Werewolf.GameEngine.Chatting.GhostMessageEvent, Werewolf.GameEngine","PlayerName":"Ramen_Fluffy","Message":"^^","Recipients":["Ramen_Fluffy","Rox","Phyton","Ellie","SavvySteve"],"GameId":"rox-319","TimeStamp":"2021-07-21T21:48:50.5784335Z"},{"__type":"Werewolf.GameEngine.Chatting.GhostMessageEvent, Werewolf.GameEngine","PlayerName":"SavvySteve","Message":"OOf","Recipients":["Ramen_Fluffy","Rox","Phyton","Ellie","SavvySteve"],"GameId":"rox-319","TimeStamp":"2021-07-21T21:48:50.6164909Z"},{"__type":"Werewolf.GameEngine.Chatting.GhostMessageEvent, Werewolf.GameEngine","PlayerName":"SavvySteve","Message":"That's a bad n1","Recipients":["Ramen_Fluffy","Rox","Phyton","Ellie","SavvySteve"],"GameId":"rox-319","TimeStamp":"2021-07-21T21:48:55.0917575Z"},{"__type":"Werewolf.GameEngine.Chatting.GhostMessageEvent, Werewolf.GameEngine","PlayerName":"Ellie","Message":"i was vanilla too","Recipients":["Ramen_Fluffy","Rox","Phyton","Ellie","SavvySteve"],"GameId":"rox-319","TimeStamp":"2021-07-21T21:48:56.1668858Z"},{"__type":"Werewolf.GameEngine.Chatting.GhostMessageEvent, Werewolf.GameEngine","PlayerName":"SavvySteve","Message":"Big oof","Recipients":["Ramen_Fluffy","Rox","Phyton","Ellie","SavvySteve"],"GameId":"rox-319","TimeStamp":"2021-07-21T21:49:02.1536807Z"},{"__type":"Werewolf.GameEngine.Chatting.GhostMessageEvent, Werewolf.GameEngine","PlayerName":"Rox","Message":"I was going to recruit you","Recipients":["Ramen_Fluffy","Rox","Phyton","Ellie","SavvySteve"],"GameId":"rox-319","TimeStamp":"2021-07-21T21:49:03.9118771Z"},{"__type":"Werewolf.GameEngine.Phases.VoteForNoLynchCast, Werewolf.GameEngine","PlayerName":"laser","GameId":"rox-319","TimeStamp":"2021-07-21T21:49:08.8753976Z"},{"__type":"Werewolf.GameEngine.Chatting.GhostMessageEvent, Werewolf.GameEngine","PlayerName":"Rox","Message":"But changed my mind","Recipients":["Ramen_Fluffy","Rox","Phyton","Ellie","SavvySteve"],"GameId":"rox-319","TimeStamp":"2021-07-21T21:49:11.0731021Z"},{"__type":"Werewolf.GameEngine.Chatting.GhostMessageEvent, Werewolf.GameEngine","PlayerName":"Ellie","Message":"me?","Recipients":["Ramen_Fluffy","Rox","Phyton","Ellie","SavvySteve"],"GameId":"rox-319","TimeStamp":"2021-07-21T21:49:16.2849416Z"},{"__type":"Werewolf.GameEngine.Chatting.GhostMessageEvent, Werewolf.GameEngine","PlayerName":"Rox","Message":"Savvy","Recipients":["Ramen_Fluffy","Rox","Phyton","Ellie","SavvySteve"],"GameId":"rox-319","TimeStamp":"2021-07-21T21:49:19.075788Z"},{"__type":"Werewolf.GameEngine.Chatting.GhostMessageEvent, Werewolf.GameEngine","PlayerName":"Ellie","Message":"oh ok","Recipients":["Ramen_Fluffy","Rox","Phyton","Ellie","SavvySteve"],"GameId":"rox-319","TimeStamp":"2021-07-21T21:49:22.3341742Z"},{"__type":"Werewolf.GameEngine.Chatting.GhostMessageEvent, Werewolf.GameEngine","PlayerName":"SavvySteve","Message":"Sadness","Recipients":["Ramen_Fluffy","Rox","Phyton","Ellie","SavvySteve"],"GameId":"rox-319","TimeStamp":"2021-07-21T21:49:22.4406804Z"},{"__type":"Werewolf.GameEngine.Chatting.GhostMessageEvent, Werewolf.GameEngine","PlayerName":"Ramen_Fluffy","Message":";-;","Recipients":["Ramen_Fluffy","Rox","Phyton","Ellie","SavvySteve"],"GameId":"rox-319","TimeStamp":"2021-07-21T21:49:53.6889645Z"},{"__type":"Werewolf.GameEngine.Chatting.GhostMessageEvent, Werewolf.GameEngine","PlayerName":"Rox","Message":"F","Recipients":["Ramen_Fluffy","Rox","Phyton","Ellie","SavvySteve"],"GameId":"rox-319","TimeStamp":"2021-07-21T21:50:04.9956982Z"},{"__type":"Werewolf.GameEngine.Chatting.GhostMessageEvent, Werewolf.GameEngine","PlayerName":"Ramen_Fluffy","Message":"lol","Recipients":["Ramen_Fluffy","Rox","Phyton","Ellie","SavvySteve"],"GameId":"rox-319","TimeStamp":"2021-07-21T21:50:44.4112886Z"},{"__type":"Werewolf.GameEngine.Phases.Day.VillageNominationEvent, Werewolf.GameEngine","PlayerName":"ShaneMcC","Target":"ImTownSRSLY","GameId":"rox-319","TimeStamp":"2021-07-21T21:51:31.494003Z"},{"__type":"Werewolf.GameEngine.Phases.Night.NightStartsSoonWarningGiven, Werewolf.GameEngine","FlavourText":"An owl hoots...","GameId":"rox-319","TimeStamp":"2021-07-21T21:51:36.1045914Z"},{"__type":"Werewolf.GameEngine.Phases.Day.VillageNominationEvent, Werewolf.GameEngine","PlayerName":"ctsk","Target":"ImTownSRSLY","GameId":"rox-319","TimeStamp":"2021-07-21T21:51:42.2285202Z"},{"__type":"Werewolf.GameEngine.Phases.VoteForNoLynchCast, Werewolf.GameEngine","PlayerName":"SnapDragon","GameId":"rox-319","TimeStamp":"2021-07-21T21:51:43.1345369Z"},{"__type":"Werewolf.GameEngine.Phases.Day.VillageNominationRetractedEvent, Werewolf.GameEngine","Target":"ImTownSRSLY","PlayerName":"ctsk","GameId":"rox-319","TimeStamp":"2021-07-21T21:51:56.8148596Z"},{"__type":"Werewolf.GameEngine.Phases.Day.VillageNominationEvent, Werewolf.GameEngine","PlayerName":"ctsk","Target":"NicolBolas","GameId":"rox-319","TimeStamp":"2021-07-21T21:51:56.8148616Z"},{"__type":"Werewolf.GameEngine.Phases.VoteForNoLynchRetracted, Werewolf.GameEngine","PlayerName":"SnapDragon","GameId":"rox-319","TimeStamp":"2021-07-21T21:52:02.7821376Z"},{"__type":"Werewolf.GameEngine.Phases.Day.VillageNominationEvent, Werewolf.GameEngine","PlayerName":"SnapDragon","Target":"NicolBolas","GameId":"rox-319","TimeStamp":"2021-07-21T21:52:02.7821395Z"},{"__type":"Werewolf.GameEngine.Phases.Night.NightStartedEvent, Werewolf.GameEngine","NightNumber":4,"PhaseLength":0,"GameId":"rox-319","TimeStamp":"2021-07-21T21:52:06.1664395Z"},{"__type":"Werewolf.GameEngine.Phases.Day.PlayerLynchedEvent, Werewolf.GameEngine","PlayerName":"NicolBolas","Message":"was executed by guillotine","GameId":"rox-319","TimeStamp":"2021-07-21T21:52:06.1667001Z"},{"__type":"Werewolf.GameEngine.PlayerActivity.WarnedForInactivity, Werewolf.GameEngine","PlayerName":"ImTownSRSLY","GameId":"rox-319","TimeStamp":"2021-07-21T21:52:06.1667167Z"},{"__type":"Werewolf.GameEngine.Roles.ValidPrimaryNightTargetsShown, Werewolf.GameEngine","PlayerWithRole":"ImTownSRSLY","PlayerNames":["SnapDragon","ctsk","ShaneMcC"],"ActionName":"Kill","Message":"The wolfpack have 1 kill tonight","DetailedDescription":null,"RoleOptions":null,"GameId":"rox-319","TimeStamp":"2021-07-21T21:52:06.1667478Z"},{"__type":"Werewolf.GameEngine.Items.ItemAvailable, Werewolf.GameEngine","ItemIndex":0,"ItemName":"Enchanted Scroll","Description":null,"DetailedDescription":["A scroll that seems to exude magic around it. There are incantations inscribed on it that you may choose to follow","This scroll may only be used once","1) Agitate the village tomorrow, forcing two executions","2) Reveal the role of any player executed by the village tomorrow"],"PlayerWithItem":"ImTownSRSLY","ActionName":"choose","PlayerNames":[],"ItemOptions":[{"__type":"Werewolf.GameEngine.Items.ItemUseOption, Werewolf.GameEngine","IconName":"Moderator","ActionName":"agitate","Description":"Agitate","Available":true},{"__type":"Werewolf.GameEngine.Items.ItemUseOption, Werewolf.GameEngine","IconName":"Moderator","ActionName":"reveal-executed-role","Description":"Reveal","Available":true}],"GameId":"rox-319","TimeStamp":"2021-07-21T21:52:06.1668162Z"},{"__type":"Werewolf.GameEngine.Roles.ValidPrimaryNightTargetsShown, Werewolf.GameEngine","PlayerWithRole":"Rox","PlayerNames":["SnapDragon","ctsk","ImTownSRSLY","ShaneMcC","laser"],"ActionName":"Recruit","Message":null,"DetailedDescription":null,"RoleOptions":null,"GameId":"rox-319","TimeStamp":"2021-07-21T21:52:06.1668346Z"},{"__type":"Werewolf.GameEngine.Roles.ValidPrimaryNightTargetsShown, Werewolf.GameEngine","PlayerWithRole":"laser","PlayerNames":["SnapDragon","ctsk","ImTownSRSLY","ShaneMcC","NicolBolas"],"ActionName":"Mark","Message":null,"DetailedDescription":null,"RoleOptions":null,"GameId":"rox-319","TimeStamp":"2021-07-21T21:52:06.166918Z"},{"__type":"Werewolf.GameEngine.Roles.ValidPrimaryNightTargetsShown, Werewolf.GameEngine","PlayerWithRole":"Ramen_Fluffy","PlayerNames":["SnapDragon","ctsk","ImTownSRSLY","ShaneMcC","laser"],"ActionName":"Protect","Message":null,"DetailedDescription":null,"RoleOptions":null,"GameId":"rox-319","TimeStamp":"2021-07-21T21:52:06.1669236Z"},{"__type":"Werewolf.GameEngine.Roles.NightTargetChosenEvent, Werewolf.GameEngine","Confirmation":"Tonight you will weave a spell for $ShaneMcC","AlliesConfirmation":null,"Allies":null,"PlayerWithRole":"SnapDragon","Role":"Spell Weaver","Target":"ShaneMcC","GameId":"rox-319","TimeStamp":"2021-07-21T21:52:08.759799Z"},{"__type":"Werewolf.GameEngine.Chatting.WerewolfNightMessageEvent, Werewolf.GameEngine","PlayerName":"laser","Message":"wel","Recipients":["ImTownSRSLY","laser"],"Eavesdroppers":[],"GameId":"rox-319","TimeStamp":"2021-07-21T21:52:14.3150746Z"},{"__type":"Werewolf.GameEngine.Chatting.GhostMessageEvent, Werewolf.GameEngine","PlayerName":"Rox","Message":"Well this is gg unless you were a wolf","Recipients":["Ramen_Fluffy","Rox","Phyton","Ellie","SavvySteve","NicolBolas"],"GameId":"rox-319","TimeStamp":"2021-07-21T21:52:15.7718284Z"},{"__type":"Werewolf.GameEngine.Chatting.WerewolfNightMessageEvent, Werewolf.GameEngine","PlayerName":"laser","Message":"this is going very well","Recipients":["ImTownSRSLY","laser"],"Eavesdroppers":[],"GameId":"rox-319","TimeStamp":"2021-07-21T21:52:17.7822972Z"},{"__type":"Werewolf.GameEngine.Chatting.WerewolfNightMessageEvent, Werewolf.GameEngine","PlayerName":"ImTownSRSLY","Message":"welll","Recipients":["ImTownSRSLY","laser"],"Eavesdroppers":[],"GameId":"rox-319","TimeStamp":"2021-07-21T21:52:18.6138189Z"},{"__type":"Werewolf.GameEngine.Roles.NightTargetChosenEvent, Werewolf.GameEngine","Confirmation":"Tonight you will mark $ctsk with wolf blood","AlliesConfirmation":"Tonight $laser will mark $ctsk with wolf blood","Allies":["ImTownSRSLY"],"PlayerWithRole":"laser","Role":"Bloodletter","Target":"ctsk","GameId":"rox-319","TimeStamp":"2021-07-21T21:52:20.159736Z"},{"__type":"Werewolf.GameEngine.Phases.Night.WerewolfVoteEvent, Werewolf.GameEngine","Werewolf":"ImTownSRSLY","Target":"ctsk","Recipients":["ImTownSRSLY","laser"],"MaxKillCount":1,"ThisKill":1,"GameId":"rox-319","TimeStamp":"2021-07-21T21:52:21.2055322Z"},{"__type":"Werewolf.GameEngine.Phases.Night.WerewolfVoteEvent, Werewolf.GameEngine","Werewolf":"ImTownSRSLY","Target":"SnapDragon","Recipients":["ImTownSRSLY","laser"],"MaxKillCount":1,"ThisKill":1,"GameId":"rox-319","TimeStamp":"2021-07-21T21:52:25.5789519Z"},{"__type":"Werewolf.GameEngine.Chatting.GhostMessageEvent, Werewolf.GameEngine","PlayerName":"NicolBolas","Message":"I didnt vote :(","Recipients":["Ramen_Fluffy","Rox","Phyton","Ellie","SavvySteve","NicolBolas"],"GameId":"rox-319","TimeStamp":"2021-07-21T21:52:27.8915093Z"},{"__type":"Werewolf.GameEngine.Phases.Day.DayStartsSoonWarningGiven, Werewolf.GameEngine","FlavourText":"Daybreak approaches...","GameId":"rox-319","TimeStamp":"2021-07-21T21:52:36.3023926Z"},{"__type":"Werewolf.GameEngine.Chatting.GhostMessageEvent, Werewolf.GameEngine","PlayerName":"NicolBolas","Message":"I should do that","Recipients":["Ramen_Fluffy","Rox","Phyton","Ellie","SavvySteve","NicolBolas"],"GameId":"rox-319","TimeStamp":"2021-07-21T21:52:45.5422217Z"},{"__type":"Werewolf.GameEngine.Roles.Werewolves.Bloodletter.PlayerMarkedByBloodletter, Werewolf.GameEngine","PlayerWithRole":"laser","Target":"ctsk","NightNumber":4,"GameId":"rox-319","TimeStamp":"2021-07-21T21:53:06.118487Z"},{"__type":"Werewolf.GameEngine.Items.EnchantedScrollAllocated, Werewolf.GameEngine","PlayerName":"ShaneMcC","ItemId":"d5e5aebe-9f7a-4aaa-a77d-c3f1ec2bb738","ItemOptions":["agitate","reveal-executed-role"],"GameId":"rox-319","TimeStamp":"2021-07-21T21:53:06.1184932Z"},{"__type":"Werewolf.GameEngine.Phases.Night.PlayerKilledEvent, Werewolf.GameEngine","PlayerName":"SnapDragon","CauseOfDeath":"Werewolf","GameId":"rox-319","TimeStamp":"2021-07-21T21:53:06.1185646Z"},{"__type":"Werewolf.GameEngine.Phases.Day.DayStartedEvent, Werewolf.GameEngine","DayNumber":5,"PhaseLength":0,"DiscussionLength":0,"GameId":"rox-319","TimeStamp":"2021-07-21T21:53:06.1185732Z"},{"__type":"Werewolf.GameEngine.Phases.Day.VillageNominationsOpenedEvent, Werewolf.GameEngine","TimeLeft":0,"GameId":"rox-319","TimeStamp":"2021-07-21T21:53:36.1737636Z"},{"__type":"Werewolf.GameEngine.Phases.Day.NoLynchOptionAvailable, Werewolf.GameEngine","GameId":"rox-319","TimeStamp":"2021-07-21T21:53:36.1737661Z"},{"__type":"Werewolf.GameEngine.Phases.Day.SkipDayOptionAvailable, Werewolf.GameEngine","GameId":"rox-319","TimeStamp":"2021-07-21T21:53:36.1737668Z"},{"__type":"Werewolf.GameEngine.Phases.After.WerewolfVictoryEvent, Werewolf.GameEngine","WinningPlayers":null,"GameId":"rox-319","TimeStamp":"2021-07-21T21:53:36.1737964Z"},{"__type":"Werewolf.GameEngine.Chatting.PostGameMessageEvent, Werewolf.GameEngine","Message":"I tried recruiting laser","PlayerName":"Rox","OriginalName":"Rox","GameId":"rox-319","TimeStamp":"2021-07-21T21:53:43.0020329Z"},{"__type":"Werewolf.GameEngine.Chatting.PostGameMessageEvent, Werewolf.GameEngine","Message":"F","PlayerName":"ShaneMcC","OriginalName":"ShaneMcC","GameId":"rox-319","TimeStamp":"2021-07-21T21:53:46.7838472Z"},{"__type":"Werewolf.GameEngine.Chatting.PostGameMessageEvent, Werewolf.GameEngine","Message":"sorry Rox","PlayerName":"laser","OriginalName":"laser","GameId":"rox-319","TimeStamp":"2021-07-21T21:53:47.7624818Z"},{"__type":"Werewolf.GameEngine.Chatting.PostGameMessageEvent, Werewolf.GameEngine","Message":"Big sad","PlayerName":"Rox","OriginalName":"Rox","GameId":"rox-319","TimeStamp":"2021-07-21T21:53:51.8743549Z"},{"__type":"Werewolf.GameEngine.Chatting.PostGameMessageEvent, Werewolf.GameEngine","Message":"sorry nicol!","PlayerName":"ctsk","OriginalName":"ctsk","GameId":"rox-319","TimeStamp":"2021-07-21T21:54:05.7919331Z"},{"__type":"Werewolf.GameEngine.Chatting.PostGameMessageEvent, Werewolf.GameEngine","Message":":(","PlayerName":"Rox","OriginalName":"Rox","GameId":"rox-319","TimeStamp":"2021-07-21T21:54:06.4179114Z"},{"__type":"Werewolf.GameEngine.Chatting.PostGameMessageEvent, Werewolf.GameEngine","Message":"I feel like I have bad luck in my own games 😛","PlayerName":"Rox","OriginalName":"Rox","GameId":"rox-319","TimeStamp":"2021-07-21T21:54:36.7428148Z"},{"__type":"Werewolf.GameEngine.Chatting.PostGameMessageEvent, Werewolf.GameEngine","Message":"Oh so I did prot someone correectly :D","PlayerName":"Ramen_Fluffy","OriginalName":"Ramen_Fluffy","GameId":"rox-319","TimeStamp":"2021-07-21T21:54:43.3748819Z"},{"__type":"Werewolf.GameEngine.Chatting.PostGameMessageEvent, Werewolf.GameEngine","Message":"Well","PlayerName":"ctsk","OriginalName":"ctsk","GameId":"rox-319","TimeStamp":"2021-07-21T21:54:50.2385699Z"},{"__type":"Werewolf.GameEngine.Chatting.PostGameMessageEvent, Werewolf.GameEngine","Message":":(","PlayerName":"Rox","OriginalName":"Rox","GameId":"rox-319","TimeStamp":"2021-07-21T21:55:02.480018Z"},{"__type":"Werewolf.GameEngine.Chatting.PostGameMessageEvent, Werewolf.GameEngine","Message":"You protected rght and wrong at the same time ","PlayerName":"ctsk","OriginalName":"ctsk","GameId":"rox-319","TimeStamp":"2021-07-21T21:55:07.0524274Z"},{"__type":"Werewolf.GameEngine.Chatting.PostGameMessageEvent, Werewolf.GameEngine","Message":"ah good work Ramen","PlayerName":"laser","OriginalName":"laser","GameId":"rox-319","TimeStamp":"2021-07-21T21:55:11.0249448Z"},{"__type":"Werewolf.GameEngine.Chatting.PostGameMessageEvent, Werewolf.GameEngine","Message":"Saving villager > saving prot?","PlayerName":"ctsk","OriginalName":"ctsk","GameId":"rox-319","TimeStamp":"2021-07-21T21:55:29.4797219Z"},{"__type":"Werewolf.GameEngine.Chatting.PostGameMessageEvent, Werewolf.GameEngine","Message":"https://werewolv.es/game/vmh-112","PlayerName":"ImTownSRSLY","OriginalName":"ImTownSRSLY","GameId":"rox-319","TimeStamp":"2021-07-21T21:55:49.5665902Z"}]